{
	"#comment": "pirate9",
	"objects": [
		{
			"objclass": "LevelDefinition",
			"objdata": {
				"RandomLevelSet": [
					"pirate/pirate0901",
					"pirate/pirate0902",
					"pirate/pirate0903",
					"pirate/pirate0904",
					"pirate/pirate0905",
					"pirate/pirate0906",
					"pirate/pirate0907",
					"pirate/pirate0908",
					"pirate/pirate0909",
					"pirate/pirate0910",
					"pirate/pirate0911",
					"pirate/pirate0912",
					"pirate/pirate0913",
					"pirate/pirate0914",
					"pirate/pirate0915",
					"pirate/pirate0916",
					"pirate/pirate0917",
					"pirate/pirate0918",
					"pirate/pirate0919",
					"pirate/pirate0920",
					"pirate/pirate0921",
					"pirate/pirate0922",
					"pirate/pirate0923",
					"pirate/pirate0924",
					"pirate/pirate0925",
					"pirate/pirate0926",
					"pirate/pirate0927",
					"pirate/pirate0928",
					"pirate/pirate0929",
					"pirate/pirate0930",
					"pirate/pirate0931",
					"pirate/pirate0932",
					"pirate/pirate0933",
					"pirate/pirate0934",
					"pirate/pirate0935",
					"pirate/pirate0936",
					"pirate/pirate0937",
					"pirate/pirate0938",
					"pirate/pirate0939",
					"pirate/pirate0940",
					"pirate/pirate0941",
					"pirate/pirate0942",
					"pirate/pirate0943",
					"pirate/pirate0944",
					"pirate/pirate0945",
					"pirate/pirate0946",
					"pirate/pirate0947",
					"pirate/pirate0948",
					"pirate/pirate0949",
					"pirate/pirate0950",
					"pirate/pirate0951",
					"pirate/pirate0952",
					"pirate/pirate0953",
					"pirate/pirate0954",
					"pirate/pirate0955",
					"pirate/pirate0956",
					"pirate/pirate0957",
					"pirate/pirate0958",
					"pirate/pirate0959",
					"pirate/pirate0960",
					"pirate/pirate0961",
					"pirate/pirate0962",
					"pirate/pirate0963",
					"pirate/pirate0964",
					"pirate/pirate0965",
					"pirate/pirate0966",
					"pirate/pirate0967",
					"pirate/pirate0968"
				]
			}
		}
	],
	"version": 1
}