{
	"###": "This Map Create By SPC-Util : Map-Designer",
	"version": 1,
	"objects": [
		{
			"objclass": "WorldData",
			"objdata": {
				"m_worldName": "future",
				"m_boundingRect": {
					"mX": 5218,
					"mY": -98,
					"mWidth": 2200,
					"mHeight": 834
				},
				"m_worldId": 5,
				"m_resGroupID": 6,
				"m_version": 1,
				"m_creationTime": 135086093,
				"m_mapPieces": [
					{
						"m_eventType": "island",
						"m_imageID": 13,
						"m_parallaxLayer": 0,
						"m_drawLayer": 0,
						"m_position": {
							"x": 7942.1875,
							"y": 357
						},
						"m_scaleX": 1,
						"m_scaleY": 1,
						"m_rotationAngle": 0,
						"m_isArtFlipped": false,
						"m_rotationRate": 0
					},
					{
						"m_eventType": "island",
						"m_imageID": 13,
						"m_parallaxLayer": 0,
						"m_drawLayer": 0,
						"m_position": {
							"x": 8715.625,
							"y": 360
						},
						"m_scaleX": 1,
						"m_scaleY": 1,
						"m_rotationAngle": 0,
						"m_isArtFlipped": false,
						"m_rotationRate": 0
					},
					{
						"m_eventType": "island",
						"m_imageID": 13,
						"m_parallaxLayer": 0,
						"m_drawLayer": 0,
						"m_position": {
							"x": 9778.905999999999,
							"y": 390
						},
						"m_scaleX": 1,
						"m_scaleY": 1,
						"m_rotationAngle": 0,
						"m_isArtFlipped": false,
						"m_rotationRate": 0
					},
					{
						"m_eventType": "island",
						"m_imageID": 13,
						"m_parallaxLayer": 0,
						"m_drawLayer": 0,
						"m_position": {
							"x": 10680.468799999999,
							"y": 381
						},
						"m_scaleX": 1,
						"m_scaleY": 1,
						"m_rotationAngle": 0,
						"m_isArtFlipped": false,
						"m_rotationRate": 0
					},
					{
						"m_eventType": "island",
						"m_imageID": 5,
						"m_parallaxLayer": 0,
						"m_drawLayer": 0,
						"m_position": {
							"x": 5983.593749999999,
							"y": 346
						},
						"m_scaleX": 1,
						"m_scaleY": 1,
						"m_rotationAngle": 0,
						"m_isArtFlipped": false,
						"m_rotationRate": 0
					},
					{
						"m_eventType": "island",
						"m_imageID": 5,
						"m_parallaxLayer": 0,
						"m_drawLayer": 0,
						"m_position": {
							"x": 6360.156250000001,
							"y": 162
						},
						"m_scaleX": 1,
						"m_scaleY": 1,
						"m_rotationAngle": 0,
						"m_isArtFlipped": false,
						"m_rotationRate": 0
					},
					{
						"m_eventType": "island",
						"m_imageID": 5,
						"m_parallaxLayer": 0,
						"m_drawLayer": 0,
						"m_position": {
							"x": 6741.40625,
							"y": 354
						},
						"m_scaleX": 1,
						"m_scaleY": 1,
						"m_rotationAngle": 0,
						"m_isArtFlipped": false,
						"m_rotationRate": 0
					},
					{
						"m_eventType": "island",
						"m_imageID": 10,
						"m_parallaxLayer": 9,
						"m_drawLayer": 0,
						"m_position": {
							"x": 5660.38916,
							"y": 167
						},
						"m_scaleX": 0.89,
						"m_scaleY": 0.89,
						"m_rotationAngle": 0,
						"m_isArtFlipped": false,
						"m_rotationRate": 2
					},
					{
						"m_eventType": "island",
						"m_imageID": 18,
						"m_parallaxLayer": 4,
						"m_drawLayer": 0,
						"m_position": {
							"x": 6427.395020000001,
							"y": 85
						},
						"m_scaleX": 0.8,
						"m_scaleY": 0.8,
						"m_rotationAngle": 0,
						"m_isArtFlipped": false,
						"m_rotationRate": -4
					},
					{
						"m_eventType": "island",
						"m_imageID": 6,
						"m_parallaxLayer": 0,
						"m_drawLayer": 1,
						"m_position": {
							"x": 5912.5,
							"y": 340
						},
						"m_scaleX": 1,
						"m_scaleY": 1,
						"m_rotationAngle": 0,
						"m_isArtFlipped": true,
						"m_rotationRate": 0
					},
					{
						"m_eventType": "island",
						"m_imageID": 6,
						"m_parallaxLayer": 0,
						"m_drawLayer": 1,
						"m_position": {
							"x": 6050,
							"y": 345
						},
						"m_scaleX": 1,
						"m_scaleY": 1,
						"m_rotationAngle": 0,
						"m_isArtFlipped": false,
						"m_rotationRate": 0
					},
					{
						"m_eventType": "island",
						"m_imageID": 6,
						"m_parallaxLayer": 0,
						"m_drawLayer": 2,
						"m_position": {
							"x": 6805.468749999999,
							"y": 351
						},
						"m_scaleX": 1,
						"m_scaleY": 1,
						"m_rotationAngle": 0,
						"m_isArtFlipped": false,
						"m_rotationRate": 0
					},
					{
						"m_eventType": "island",
						"m_imageID": 5,
						"m_parallaxLayer": 0,
						"m_drawLayer": 0,
						"m_position": {
							"x": 7558.593749999999,
							"y": 235
						},
						"m_scaleX": 1,
						"m_scaleY": 1,
						"m_rotationAngle": 0,
						"m_isArtFlipped": false,
						"m_rotationRate": 0
					},
					{
						"m_eventType": "island",
						"m_imageID": 4,
						"m_parallaxLayer": 0,
						"m_drawLayer": 0,
						"m_position": {
							"x": 7691.40625,
							"y": 296
						},
						"m_scaleX": 1,
						"m_scaleY": 1,
						"m_rotationAngle": 0,
						"m_isArtFlipped": true,
						"m_rotationRate": 0
					},
					{
						"m_eventType": "island",
						"m_imageID": 5,
						"m_parallaxLayer": 0,
						"m_drawLayer": 0,
						"m_position": {
							"x": 7826.562500000001,
							"y": 351
						},
						"m_scaleX": 1,
						"m_scaleY": 1,
						"m_rotationAngle": 0,
						"m_isArtFlipped": false,
						"m_rotationRate": 0
					},
					{
						"m_eventType": "island",
						"m_imageID": 4,
						"m_parallaxLayer": 0,
						"m_drawLayer": 0,
						"m_position": {
							"x": 7957.812500000001,
							"y": 291
						},
						"m_scaleX": 1,
						"m_scaleY": 1,
						"m_rotationAngle": 0,
						"m_isArtFlipped": false,
						"m_rotationRate": 0
					},
					{
						"m_eventType": "island",
						"m_imageID": 4,
						"m_parallaxLayer": 0,
						"m_drawLayer": 0,
						"m_position": {
							"x": 8074.218749999999,
							"y": 224
						},
						"m_scaleX": 1,
						"m_scaleY": 1,
						"m_rotationAngle": 0,
						"m_isArtFlipped": false,
						"m_rotationRate": 0
					},
					{
						"m_eventType": "island",
						"m_imageID": 5,
						"m_parallaxLayer": 0,
						"m_drawLayer": 0,
						"m_position": {
							"x": 8197.655999999999,
							"y": 163
						},
						"m_scaleX": 1,
						"m_scaleY": 1,
						"m_rotationAngle": 0,
						"m_isArtFlipped": false,
						"m_rotationRate": 0
					},
					{
						"m_eventType": "island",
						"m_imageID": 4,
						"m_parallaxLayer": 0,
						"m_drawLayer": 0,
						"m_position": {
							"x": 8328.905999999999,
							"y": 227
						},
						"m_scaleX": 1,
						"m_scaleY": 1,
						"m_rotationAngle": 0,
						"m_isArtFlipped": true,
						"m_rotationRate": 0
					},
					{
						"m_eventType": "island",
						"m_imageID": 4,
						"m_parallaxLayer": 0,
						"m_drawLayer": 0,
						"m_position": {
							"x": 8447.655999999999,
							"y": 295
						},
						"m_scaleX": 1,
						"m_scaleY": 1,
						"m_rotationAngle": 0,
						"m_isArtFlipped": true,
						"m_rotationRate": 0
					},
					{
						"m_eventType": "island",
						"m_imageID": 5,
						"m_parallaxLayer": 0,
						"m_drawLayer": 0,
						"m_position": {
							"x": 8579.6875,
							"y": 352
						},
						"m_scaleX": 1,
						"m_scaleY": 1,
						"m_rotationAngle": 0,
						"m_isArtFlipped": false,
						"m_rotationRate": 0
					},
					{
						"m_eventType": "island",
						"m_imageID": 4,
						"m_parallaxLayer": 0,
						"m_drawLayer": 0,
						"m_position": {
							"x": 8713.281,
							"y": 293
						},
						"m_scaleX": 1,
						"m_scaleY": 1,
						"m_rotationAngle": 0,
						"m_isArtFlipped": false,
						"m_rotationRate": 0
					},
					{
						"m_eventType": "island",
						"m_imageID": 4,
						"m_parallaxLayer": 0,
						"m_drawLayer": 0,
						"m_position": {
							"x": 8832.8125,
							"y": 226
						},
						"m_scaleX": 1,
						"m_scaleY": 1,
						"m_rotationAngle": 0,
						"m_isArtFlipped": false,
						"m_rotationRate": 0
					},
					{
						"m_eventType": "island",
						"m_imageID": 5,
						"m_parallaxLayer": 0,
						"m_drawLayer": 0,
						"m_position": {
							"x": 8960.9375,
							"y": 165
						},
						"m_scaleX": 1,
						"m_scaleY": 1,
						"m_rotationAngle": 0,
						"m_isArtFlipped": false,
						"m_rotationRate": 0
					},
					{
						"m_eventType": "island",
						"m_imageID": 4,
						"m_parallaxLayer": 0,
						"m_drawLayer": 0,
						"m_position": {
							"x": 9092.969,
							"y": 228
						},
						"m_scaleX": 1,
						"m_scaleY": 1,
						"m_rotationAngle": 0,
						"m_isArtFlipped": true,
						"m_rotationRate": 0
					},
					{
						"m_eventType": "island",
						"m_imageID": 4,
						"m_parallaxLayer": 0,
						"m_drawLayer": 0,
						"m_position": {
							"x": 9210.9375,
							"y": 295
						},
						"m_scaleX": 1,
						"m_scaleY": 1,
						"m_rotationAngle": 0,
						"m_isArtFlipped": true,
						"m_rotationRate": 0
					},
					{
						"m_eventType": "island",
						"m_imageID": 5,
						"m_parallaxLayer": 0,
						"m_drawLayer": 0,
						"m_position": {
							"x": 9342.969,
							"y": 354
						},
						"m_scaleX": 1,
						"m_scaleY": 1,
						"m_rotationAngle": 0,
						"m_isArtFlipped": false,
						"m_rotationRate": 0
					},
					{
						"m_eventType": "island",
						"m_imageID": 4,
						"m_parallaxLayer": 0,
						"m_drawLayer": 0,
						"m_position": {
							"x": 9470.3125,
							"y": 297
						},
						"m_scaleX": 1,
						"m_scaleY": 1,
						"m_rotationAngle": 0,
						"m_isArtFlipped": false,
						"m_rotationRate": 0
					},
					{
						"m_eventType": "island",
						"m_imageID": 4,
						"m_parallaxLayer": 0,
						"m_drawLayer": 0,
						"m_position": {
							"x": 9588.281,
							"y": 231
						},
						"m_scaleX": 1,
						"m_scaleY": 1,
						"m_rotationAngle": 0,
						"m_isArtFlipped": false,
						"m_rotationRate": 0
					},
					{
						"m_eventType": "island",
						"m_imageID": 5,
						"m_parallaxLayer": 0,
						"m_drawLayer": 0,
						"m_position": {
							"x": 9717.1875,
							"y": 171
						},
						"m_scaleX": 1,
						"m_scaleY": 1,
						"m_rotationAngle": 0,
						"m_isArtFlipped": false,
						"m_rotationRate": 0
					},
					{
						"m_eventType": "island",
						"m_imageID": 4,
						"m_parallaxLayer": 0,
						"m_drawLayer": 0,
						"m_position": {
							"x": 9848.4375,
							"y": 235
						},
						"m_scaleX": 1,
						"m_scaleY": 1,
						"m_rotationAngle": 0,
						"m_isArtFlipped": true,
						"m_rotationRate": 0
					},
					{
						"m_eventType": "island",
						"m_imageID": 4,
						"m_parallaxLayer": 0,
						"m_drawLayer": 0,
						"m_position": {
							"x": 9967.1875,
							"y": 302
						},
						"m_scaleX": 1,
						"m_scaleY": 1,
						"m_rotationAngle": 0,
						"m_isArtFlipped": true,
						"m_rotationRate": 0
					},
					{
						"m_eventType": "island",
						"m_imageID": 5,
						"m_parallaxLayer": 0,
						"m_drawLayer": 0,
						"m_position": {
							"x": 10096.0938,
							"y": 363
						},
						"m_scaleX": 1,
						"m_scaleY": 1,
						"m_rotationAngle": 0,
						"m_isArtFlipped": false,
						"m_rotationRate": 0
					},
					{
						"m_eventType": "island",
						"m_imageID": 4,
						"m_parallaxLayer": 0,
						"m_drawLayer": 0,
						"m_position": {
							"x": 10222.656299999999,
							"y": 300
						},
						"m_scaleX": 1,
						"m_scaleY": 1,
						"m_rotationAngle": 0,
						"m_isArtFlipped": false,
						"m_rotationRate": 0
					},
					{
						"m_eventType": "island",
						"m_imageID": 5,
						"m_parallaxLayer": 0,
						"m_drawLayer": 0,
						"m_position": {
							"x": 10466.406299999999,
							"y": 169
						},
						"m_scaleX": 1,
						"m_scaleY": 1,
						"m_rotationAngle": 0,
						"m_isArtFlipped": false,
						"m_rotationRate": 0
					},
					{
						"m_eventType": "island",
						"m_imageID": 4,
						"m_parallaxLayer": 0,
						"m_drawLayer": 0,
						"m_position": {
							"x": 10341.406299999999,
							"y": 233
						},
						"m_scaleX": 1,
						"m_scaleY": 1,
						"m_rotationAngle": 0,
						"m_isArtFlipped": false,
						"m_rotationRate": 0
					},
					{
						"m_eventType": "island",
						"m_imageID": 1,
						"m_parallaxLayer": 9,
						"m_drawLayer": 0,
						"m_position": {
							"x": 6404.29541,
							"y": 118
						},
						"m_scaleX": 0.8500000000000001,
						"m_scaleY": 0.8500000000000001,
						"m_rotationAngle": 0,
						"m_isArtFlipped": false,
						"m_rotationRate": 0
					},
					{
						"m_eventType": "island",
						"m_imageID": 101,
						"m_parallaxLayer": 0,
						"m_drawLayer": -3,
						"m_position": {
							"x": 7285.156250000001,
							"y": 404
						},
						"m_scaleX": 1.7000000000000002,
						"m_scaleY": 1.7000000000000002,
						"m_rotationAngle": 0,
						"m_isArtFlipped": false,
						"m_rotationRate": 0
					},
					{
						"m_eventType": "island",
						"m_imageID": 4,
						"m_parallaxLayer": 0,
						"m_drawLayer": 0,
						"m_position": {
							"x": 5853.125000000001,
							"y": 288
						},
						"m_scaleX": 1,
						"m_scaleY": 1,
						"m_rotationAngle": 0,
						"m_isArtFlipped": true,
						"m_rotationRate": 0
					},
					{
						"m_eventType": "island",
						"m_imageID": 4,
						"m_parallaxLayer": 0,
						"m_drawLayer": 0,
						"m_position": {
							"x": 6114.062500000001,
							"y": 291
						},
						"m_scaleX": 1,
						"m_scaleY": 1,
						"m_rotationAngle": 0,
						"m_isArtFlipped": false,
						"m_rotationRate": 0
					},
					{
						"m_eventType": "island",
						"m_imageID": 4,
						"m_parallaxLayer": 0,
						"m_drawLayer": 0,
						"m_position": {
							"x": 6233.593749999999,
							"y": 224
						},
						"m_scaleX": 1,
						"m_scaleY": 1,
						"m_rotationAngle": 0,
						"m_isArtFlipped": false,
						"m_rotationRate": 0
					},
					{
						"m_eventType": "island",
						"m_imageID": 7,
						"m_parallaxLayer": 0,
						"m_drawLayer": 1,
						"m_position": {
							"x": 6300,
							"y": 219
						},
						"m_scaleX": 1,
						"m_scaleY": 1,
						"m_rotationAngle": 0,
						"m_isArtFlipped": true,
						"m_rotationRate": 0
					},
					{
						"m_eventType": "island",
						"m_imageID": 4,
						"m_parallaxLayer": 0,
						"m_drawLayer": 0,
						"m_position": {
							"x": 6490.625000000001,
							"y": 226
						},
						"m_scaleX": 1,
						"m_scaleY": 1,
						"m_rotationAngle": 0,
						"m_isArtFlipped": true,
						"m_rotationRate": 0
					},
					{
						"m_eventType": "island",
						"m_imageID": 7,
						"m_parallaxLayer": 0,
						"m_drawLayer": 2,
						"m_position": {
							"x": 6421.093749999999,
							"y": 218
						},
						"m_scaleX": 1,
						"m_scaleY": 1,
						"m_rotationAngle": 0,
						"m_isArtFlipped": false,
						"m_rotationRate": 0
					},
					{
						"m_eventType": "island",
						"m_imageID": 102,
						"m_parallaxLayer": 0,
						"m_drawLayer": -2,
						"m_position": {
							"x": 5978.90625,
							"y": 483
						},
						"m_scaleX": 1,
						"m_scaleY": 1,
						"m_rotationAngle": 0,
						"m_isArtFlipped": false,
						"m_rotationRate": 0
					},
					{
						"m_eventType": "island",
						"m_imageID": 102,
						"m_parallaxLayer": 0,
						"m_drawLayer": -2,
						"m_position": {
							"x": 6355.468749999999,
							"y": 301
						},
						"m_scaleX": 1,
						"m_scaleY": 1,
						"m_rotationAngle": 0,
						"m_isArtFlipped": false,
						"m_rotationRate": 0
					},
					{
						"m_eventType": "island",
						"m_imageID": 4,
						"m_parallaxLayer": 0,
						"m_drawLayer": 0,
						"m_position": {
							"x": 6609.375,
							"y": 293
						},
						"m_scaleX": 1,
						"m_scaleY": 1,
						"m_rotationAngle": 0,
						"m_isArtFlipped": true,
						"m_rotationRate": 0
					},
					{
						"m_eventType": "island",
						"m_imageID": 6,
						"m_parallaxLayer": 0,
						"m_drawLayer": 1,
						"m_position": {
							"x": 6673.437499999999,
							"y": 348
						},
						"m_scaleX": 1,
						"m_scaleY": 1,
						"m_rotationAngle": 0,
						"m_isArtFlipped": true,
						"m_rotationRate": 0
					},
					{
						"m_eventType": "island",
						"m_imageID": 102,
						"m_parallaxLayer": 0,
						"m_drawLayer": -2,
						"m_position": {
							"x": 6736.718749999999,
							"y": 492
						},
						"m_scaleX": 1,
						"m_scaleY": 1,
						"m_rotationAngle": 0,
						"m_isArtFlipped": false,
						"m_rotationRate": 0
					},
					{
						"m_eventType": "island",
						"m_imageID": 101,
						"m_parallaxLayer": 0,
						"m_drawLayer": 3,
						"m_position": {
							"x": 6363.28125,
							"y": 277
						},
						"m_scaleX": 1,
						"m_scaleY": 1,
						"m_rotationAngle": 325,
						"m_isArtFlipped": false,
						"m_rotationRate": 0
					},
					{
						"m_eventType": "island",
						"m_imageID": 101,
						"m_parallaxLayer": 0,
						"m_drawLayer": 3,
						"m_position": {
							"x": 6392.968749999999,
							"y": 273
						},
						"m_scaleX": 1,
						"m_scaleY": 1,
						"m_rotationAngle": 335,
						"m_isArtFlipped": false,
						"m_rotationRate": 0
					},
					{
						"m_eventType": "island",
						"m_imageID": 101,
						"m_parallaxLayer": 0,
						"m_drawLayer": 3,
						"m_position": {
							"x": 6321.093749999999,
							"y": 268
						},
						"m_scaleX": 1,
						"m_scaleY": 1,
						"m_rotationAngle": 290,
						"m_isArtFlipped": false,
						"m_rotationRate": 0
					},
					{
						"m_eventType": "island",
						"m_imageID": 101,
						"m_parallaxLayer": 0,
						"m_drawLayer": 2,
						"m_position": {
							"x": 6453.125000000001,
							"y": 300
						},
						"m_scaleX": 1,
						"m_scaleY": 1,
						"m_rotationAngle": 0,
						"m_isArtFlipped": false,
						"m_rotationRate": 0
					},
					{
						"m_eventType": "island",
						"m_imageID": 101,
						"m_parallaxLayer": 0,
						"m_drawLayer": 2,
						"m_position": {
							"x": 6572.656250000001,
							"y": 367
						},
						"m_scaleX": 1,
						"m_scaleY": 1,
						"m_rotationAngle": 0,
						"m_isArtFlipped": false,
						"m_rotationRate": 0
					},
					{
						"m_eventType": "island",
						"m_imageID": 101,
						"m_parallaxLayer": 0,
						"m_drawLayer": 2,
						"m_position": {
							"x": 6271.093749999999,
							"y": 297
						},
						"m_scaleX": 1,
						"m_scaleY": 1,
						"m_rotationAngle": 0,
						"m_isArtFlipped": false,
						"m_rotationRate": 0
					},
					{
						"m_eventType": "island",
						"m_imageID": 101,
						"m_parallaxLayer": 0,
						"m_drawLayer": 2,
						"m_position": {
							"x": 6151.562500000001,
							"y": 367
						},
						"m_scaleX": 1,
						"m_scaleY": 1,
						"m_rotationAngle": 0,
						"m_isArtFlipped": false,
						"m_rotationRate": 0
					},
					{
						"m_eventType": "island",
						"m_imageID": 101,
						"m_parallaxLayer": 0,
						"m_drawLayer": 2,
						"m_position": {
							"x": 6015.625000000001,
							"y": 457
						},
						"m_scaleX": 1,
						"m_scaleY": 1,
						"m_rotationAngle": 335,
						"m_isArtFlipped": false,
						"m_rotationRate": 0
					},
					{
						"m_eventType": "island",
						"m_imageID": 101,
						"m_parallaxLayer": 0,
						"m_drawLayer": 2,
						"m_position": {
							"x": 5985.156250000001,
							"y": 460
						},
						"m_scaleX": 1,
						"m_scaleY": 1,
						"m_rotationAngle": 325,
						"m_isArtFlipped": false,
						"m_rotationRate": 0
					},
					{
						"m_eventType": "island",
						"m_imageID": 101,
						"m_parallaxLayer": 0,
						"m_drawLayer": 2,
						"m_position": {
							"x": 5944.53125,
							"y": 453
						},
						"m_scaleX": 1,
						"m_scaleY": 1,
						"m_rotationAngle": 20,
						"m_isArtFlipped": false,
						"m_rotationRate": 0
					},
					{
						"m_eventType": "island",
						"m_imageID": 101,
						"m_parallaxLayer": 0,
						"m_drawLayer": 2,
						"m_position": {
							"x": 5815.625000000001,
							"y": 363
						},
						"m_scaleX": 1,
						"m_scaleY": 1,
						"m_rotationAngle": 0,
						"m_isArtFlipped": false,
						"m_rotationRate": 0
					},
					{
						"m_eventType": "island",
						"m_imageID": 4,
						"m_parallaxLayer": 0,
						"m_drawLayer": 0,
						"m_position": {
							"x": 6872.656250000001,
							"y": 295
						},
						"m_scaleX": 1,
						"m_scaleY": 1,
						"m_rotationAngle": 0,
						"m_isArtFlipped": false,
						"m_rotationRate": 0
					},
					{
						"m_eventType": "island",
						"m_imageID": 5,
						"m_parallaxLayer": 0,
						"m_drawLayer": -1,
						"m_position": {
							"x": 7002.343749999999,
							"y": 232
						},
						"m_scaleX": 1,
						"m_scaleY": 1,
						"m_rotationAngle": 0,
						"m_isArtFlipped": false,
						"m_rotationRate": 0
					},
					{
						"m_eventType": "island",
						"m_imageID": 7,
						"m_parallaxLayer": 0,
						"m_drawLayer": 0,
						"m_position": {
							"x": 6944.53125,
							"y": 287
						},
						"m_scaleX": 1,
						"m_scaleY": 1,
						"m_rotationAngle": 0,
						"m_isArtFlipped": true,
						"m_rotationRate": 0
					},
					{
						"m_eventType": "island",
						"m_imageID": 21,
						"m_parallaxLayer": 10,
						"m_drawLayer": 0,
						"m_position": {
							"x": 5614.581543,
							"y": 52
						},
						"m_scaleX": 1,
						"m_scaleY": 1,
						"m_rotationAngle": 0,
						"m_isArtFlipped": false,
						"m_rotationRate": 0
					},
					{
						"m_eventType": "island",
						"m_imageID": 10,
						"m_parallaxLayer": 9,
						"m_drawLayer": 0,
						"m_position": {
							"x": 5904.76416,
							"y": 189
						},
						"m_scaleX": 0.8,
						"m_scaleY": 0.8,
						"m_rotationAngle": 230,
						"m_isArtFlipped": false,
						"m_rotationRate": -3
					},
					{
						"m_eventType": "island",
						"m_imageID": 9,
						"m_parallaxLayer": 9,
						"m_drawLayer": 0,
						"m_position": {
							"x": 5385.935546999999,
							"y": 128
						},
						"m_scaleX": 0.7500000000000001,
						"m_scaleY": 0.7500000000000001,
						"m_rotationAngle": 0,
						"m_isArtFlipped": false,
						"m_rotationRate": -2
					},
					{
						"m_eventType": "island",
						"m_imageID": 102,
						"m_parallaxLayer": 0,
						"m_drawLayer": -1,
						"m_position": {
							"x": 5698.437499999999,
							"y": 396
						},
						"m_scaleX": 0.30000000000000004,
						"m_scaleY": 0.30000000000000004,
						"m_rotationAngle": 0,
						"m_isArtFlipped": false,
						"m_rotationRate": 0
					},
					{
						"m_eventType": "island",
						"m_imageID": 102,
						"m_parallaxLayer": 0,
						"m_drawLayer": -1,
						"m_position": {
							"x": 5573.437499999999,
							"y": 349
						},
						"m_scaleX": 0.30000000000000004,
						"m_scaleY": 0.30000000000000004,
						"m_rotationAngle": 0,
						"m_isArtFlipped": false,
						"m_rotationRate": 0
					},
					{
						"m_eventType": "island",
						"m_imageID": 9,
						"m_parallaxLayer": 9,
						"m_drawLayer": 0,
						"m_position": {
							"x": 6020.70166,
							"y": 147
						},
						"m_scaleX": 0.8,
						"m_scaleY": 0.8,
						"m_rotationAngle": 280,
						"m_isArtFlipped": false,
						"m_rotationRate": 2
					},
					{
						"m_eventType": "island",
						"m_imageID": 103,
						"m_parallaxLayer": 2,
						"m_drawLayer": 0,
						"m_position": {
							"x": 5596.041016,
							"y": 153
						},
						"m_scaleX": 0.8,
						"m_scaleY": 0.8,
						"m_rotationAngle": 0,
						"m_isArtFlipped": false,
						"m_rotationRate": 0
					},
					{
						"m_eventType": "island",
						"m_imageID": 17,
						"m_parallaxLayer": 4,
						"m_drawLayer": 0,
						"m_position": {
							"x": 6429.738769999999,
							"y": 132
						},
						"m_scaleX": 0.8,
						"m_scaleY": 0.8,
						"m_rotationAngle": 345,
						"m_isArtFlipped": false,
						"m_rotationRate": 0
					},
					{
						"m_eventType": "island",
						"m_imageID": 6,
						"m_parallaxLayer": 0,
						"m_drawLayer": 2,
						"m_position": {
							"x": 7891.40625,
							"y": 346
						},
						"m_scaleX": 1,
						"m_scaleY": 1,
						"m_rotationAngle": 0,
						"m_isArtFlipped": false,
						"m_rotationRate": 0
					},
					{
						"m_eventType": "island",
						"m_imageID": 6,
						"m_parallaxLayer": 0,
						"m_drawLayer": 2,
						"m_position": {
							"x": 7753.125000000001,
							"y": 349
						},
						"m_scaleX": 1,
						"m_scaleY": 1,
						"m_rotationAngle": 0,
						"m_isArtFlipped": true,
						"m_rotationRate": 0
					},
					{
						"m_eventType": "island",
						"m_imageID": 7,
						"m_parallaxLayer": 0,
						"m_drawLayer": 2,
						"m_position": {
							"x": 7626.562500000001,
							"y": 291
						},
						"m_scaleX": 1,
						"m_scaleY": 1,
						"m_rotationAngle": 0,
						"m_isArtFlipped": false,
						"m_rotationRate": 0
					},
					{
						"m_eventType": "island",
						"m_imageID": 7,
						"m_parallaxLayer": 0,
						"m_drawLayer": 2,
						"m_position": {
							"x": 8138.28125,
							"y": 219
						},
						"m_scaleX": 1,
						"m_scaleY": 1,
						"m_rotationAngle": 0,
						"m_isArtFlipped": true,
						"m_rotationRate": 0
					},
					{
						"m_eventType": "island",
						"m_imageID": 7,
						"m_parallaxLayer": 0,
						"m_drawLayer": 2,
						"m_position": {
							"x": 8260.9375,
							"y": 221
						},
						"m_scaleX": 1,
						"m_scaleY": 1,
						"m_rotationAngle": 0,
						"m_isArtFlipped": false,
						"m_rotationRate": 0
					},
					{
						"m_eventType": "island",
						"m_imageID": 6,
						"m_parallaxLayer": 0,
						"m_drawLayer": 2,
						"m_position": {
							"x": 8507.8125,
							"y": 347
						},
						"m_scaleX": 1,
						"m_scaleY": 1,
						"m_rotationAngle": 0,
						"m_isArtFlipped": true,
						"m_rotationRate": 0
					},
					{
						"m_eventType": "island",
						"m_imageID": 6,
						"m_parallaxLayer": 0,
						"m_drawLayer": 2,
						"m_position": {
							"x": 8644.531,
							"y": 350
						},
						"m_scaleX": 1,
						"m_scaleY": 1,
						"m_rotationAngle": 0,
						"m_isArtFlipped": false,
						"m_rotationRate": 0
					},
					{
						"m_eventType": "island",
						"m_imageID": 6,
						"m_parallaxLayer": 0,
						"m_drawLayer": 2,
						"m_position": {
							"x": 9271.094000000001,
							"y": 348
						},
						"m_scaleX": 1,
						"m_scaleY": 1,
						"m_rotationAngle": 0,
						"m_isArtFlipped": true,
						"m_rotationRate": 0
					},
					{
						"m_eventType": "island",
						"m_imageID": 6,
						"m_parallaxLayer": 0,
						"m_drawLayer": 2,
						"m_position": {
							"x": 9406.25,
							"y": 352
						},
						"m_scaleX": 1,
						"m_scaleY": 1,
						"m_rotationAngle": 0,
						"m_isArtFlipped": false,
						"m_rotationRate": 0
					},
					{
						"m_eventType": "island",
						"m_imageID": 7,
						"m_parallaxLayer": 0,
						"m_drawLayer": 2,
						"m_position": {
							"x": 8898.4375,
							"y": 221
						},
						"m_scaleX": 1,
						"m_scaleY": 1,
						"m_rotationAngle": 0,
						"m_isArtFlipped": true,
						"m_rotationRate": 0
					},
					{
						"m_eventType": "island",
						"m_imageID": 7,
						"m_parallaxLayer": 0,
						"m_drawLayer": 2,
						"m_position": {
							"x": 9021.874999999998,
							"y": 221
						},
						"m_scaleX": 1,
						"m_scaleY": 1,
						"m_rotationAngle": 0,
						"m_isArtFlipped": false,
						"m_rotationRate": 0
					},
					{
						"m_eventType": "island",
						"m_imageID": 7,
						"m_parallaxLayer": 0,
						"m_drawLayer": 2,
						"m_position": {
							"x": 9653.905999999999,
							"y": 227
						},
						"m_scaleX": 1,
						"m_scaleY": 1,
						"m_rotationAngle": 0,
						"m_isArtFlipped": true,
						"m_rotationRate": 0
					},
					{
						"m_eventType": "island",
						"m_imageID": 7,
						"m_parallaxLayer": 0,
						"m_drawLayer": 2,
						"m_position": {
							"x": 9778.905999999999,
							"y": 228
						},
						"m_scaleX": 1,
						"m_scaleY": 1,
						"m_rotationAngle": 0,
						"m_isArtFlipped": false,
						"m_rotationRate": 0
					},
					{
						"m_eventType": "island",
						"m_imageID": 6,
						"m_parallaxLayer": 0,
						"m_drawLayer": 2,
						"m_position": {
							"x": 10029.6875,
							"y": 356
						},
						"m_scaleX": 1,
						"m_scaleY": 1,
						"m_rotationAngle": 0,
						"m_isArtFlipped": true,
						"m_rotationRate": 0
					},
					{
						"m_eventType": "island",
						"m_imageID": 6,
						"m_parallaxLayer": 0,
						"m_drawLayer": 2,
						"m_position": {
							"x": 10155.468799999999,
							"y": 357
						},
						"m_scaleX": 1,
						"m_scaleY": 1,
						"m_rotationAngle": 0,
						"m_isArtFlipped": false,
						"m_rotationRate": 0
					},
					{
						"m_eventType": "island",
						"m_imageID": 7,
						"m_parallaxLayer": 0,
						"m_drawLayer": 2,
						"m_position": {
							"x": 10408.5938,
							"y": 228
						},
						"m_scaleX": 1,
						"m_scaleY": 1,
						"m_rotationAngle": 0,
						"m_isArtFlipped": true,
						"m_rotationRate": 0
					},
					{
						"m_eventType": "island",
						"m_imageID": 10,
						"m_parallaxLayer": 9,
						"m_drawLayer": 0,
						"m_position": {
							"x": 6156.63916,
							"y": 167
						},
						"m_scaleX": 0.9,
						"m_scaleY": 0.9,
						"m_rotationAngle": 0,
						"m_isArtFlipped": false,
						"m_rotationRate": -1
					},
					{
						"m_eventType": "island",
						"m_imageID": 9,
						"m_parallaxLayer": 9,
						"m_drawLayer": 0,
						"m_position": {
							"x": 6267.57666,
							"y": 132
						},
						"m_scaleX": 0.8,
						"m_scaleY": 0.8,
						"m_rotationAngle": 0,
						"m_isArtFlipped": false,
						"m_rotationRate": 2
					},
					{
						"m_eventType": "island",
						"m_imageID": 9,
						"m_parallaxLayer": 9,
						"m_drawLayer": 0,
						"m_position": {
							"x": 6370.70166,
							"y": 138
						},
						"m_scaleX": 0.8,
						"m_scaleY": 0.8,
						"m_rotationAngle": 265,
						"m_isArtFlipped": false,
						"m_rotationRate": -2
					},
					{
						"m_eventType": "island",
						"m_imageID": 102,
						"m_parallaxLayer": 0,
						"m_drawLayer": -3,
						"m_position": {
							"x": 6996.093749999999,
							"y": 353
						},
						"m_scaleX": 1,
						"m_scaleY": 1,
						"m_rotationAngle": 0,
						"m_isArtFlipped": false,
						"m_rotationRate": 0
					},
					{
						"m_eventType": "island",
						"m_imageID": 102,
						"m_parallaxLayer": 0,
						"m_drawLayer": -1,
						"m_position": {
							"x": 7553.90625,
							"y": 378
						},
						"m_scaleX": 1,
						"m_scaleY": 1,
						"m_rotationAngle": 0,
						"m_isArtFlipped": false,
						"m_rotationRate": 0
					},
					{
						"m_eventType": "island",
						"m_imageID": 102,
						"m_parallaxLayer": 0,
						"m_drawLayer": -3,
						"m_position": {
							"x": 7818.75,
							"y": 488
						},
						"m_scaleX": 1,
						"m_scaleY": 1,
						"m_rotationAngle": 0,
						"m_isArtFlipped": false,
						"m_rotationRate": 0
					},
					{
						"m_eventType": "island",
						"m_imageID": 102,
						"m_parallaxLayer": 0,
						"m_drawLayer": -3,
						"m_position": {
							"x": 8190.625000000001,
							"y": 303
						},
						"m_scaleX": 1,
						"m_scaleY": 1,
						"m_rotationAngle": 0,
						"m_isArtFlipped": false,
						"m_rotationRate": 0
					},
					{
						"m_eventType": "island",
						"m_imageID": 102,
						"m_parallaxLayer": 0,
						"m_drawLayer": -3,
						"m_position": {
							"x": 8571.874999999998,
							"y": 487
						},
						"m_scaleX": 1,
						"m_scaleY": 1,
						"m_rotationAngle": 0,
						"m_isArtFlipped": false,
						"m_rotationRate": 0
					},
					{
						"m_eventType": "island",
						"m_imageID": 102,
						"m_parallaxLayer": 0,
						"m_drawLayer": -3,
						"m_position": {
							"x": 8950,
							"y": 299
						},
						"m_scaleX": 1,
						"m_scaleY": 1,
						"m_rotationAngle": 0,
						"m_isArtFlipped": false,
						"m_rotationRate": 0
					},
					{
						"m_eventType": "island",
						"m_imageID": 102,
						"m_parallaxLayer": 0,
						"m_drawLayer": -3,
						"m_position": {
							"x": 9335.9375,
							"y": 492
						},
						"m_scaleX": 1,
						"m_scaleY": 1,
						"m_rotationAngle": 0,
						"m_isArtFlipped": false,
						"m_rotationRate": 0
					},
					{
						"m_eventType": "island",
						"m_imageID": 102,
						"m_parallaxLayer": 0,
						"m_drawLayer": -3,
						"m_position": {
							"x": 9710.155999999999,
							"y": 310
						},
						"m_scaleX": 1,
						"m_scaleY": 1,
						"m_rotationAngle": 0,
						"m_isArtFlipped": false,
						"m_rotationRate": 0
					},
					{
						"m_eventType": "island",
						"m_imageID": 102,
						"m_parallaxLayer": 0,
						"m_drawLayer": -3,
						"m_position": {
							"x": 10092.1875,
							"y": 501
						},
						"m_scaleX": 1,
						"m_scaleY": 1,
						"m_rotationAngle": 0,
						"m_isArtFlipped": false,
						"m_rotationRate": 0
					},
					{
						"m_eventType": "island",
						"m_imageID": 102,
						"m_parallaxLayer": 0,
						"m_drawLayer": -3,
						"m_position": {
							"x": 10461.7188,
							"y": 306
						},
						"m_scaleX": 1,
						"m_scaleY": 1,
						"m_rotationAngle": 0,
						"m_isArtFlipped": false,
						"m_rotationRate": 0
					},
					{
						"m_eventType": "island",
						"m_imageID": 8,
						"m_parallaxLayer": 5,
						"m_drawLayer": 0,
						"m_position": {
							"x": 7555.337890999999,
							"y": 103
						},
						"m_scaleX": 0.6500000000000001,
						"m_scaleY": 0.6500000000000001,
						"m_rotationAngle": 0,
						"m_isArtFlipped": false,
						"m_rotationRate": 0
					},
					{
						"m_eventType": "island",
						"m_imageID": 106,
						"m_parallaxLayer": 0,
						"m_drawLayer": 0,
						"m_position": {
							"x": 5654.6875,
							"y": 262
						},
						"m_scaleX": 1,
						"m_scaleY": 1,
						"m_rotationAngle": 0,
						"m_isArtFlipped": false,
						"m_rotationRate": 0
					},
					{
						"m_eventType": "island",
						"m_imageID": 11,
						"m_parallaxLayer": 5,
						"m_drawLayer": 0,
						"m_position": {
							"x": 6719.791016,
							"y": 210
						},
						"m_scaleX": 0.5,
						"m_scaleY": 0.5,
						"m_rotationAngle": 0,
						"m_isArtFlipped": false,
						"m_rotationRate": 5
					},
					{
						"m_eventType": "island",
						"m_imageID": 12,
						"m_parallaxLayer": -3,
						"m_drawLayer": 0,
						"m_position": {
							"x": 8968.750977,
							"y": 356
						},
						"m_scaleX": 0.6000000000000001,
						"m_scaleY": 0.6000000000000001,
						"m_rotationAngle": 0,
						"m_isArtFlipped": false,
						"m_rotationRate": -7
					},
					{
						"m_eventType": "island",
						"m_imageID": 12,
						"m_parallaxLayer": -4,
						"m_drawLayer": 0,
						"m_position": {
							"x": 12341.980469,
							"y": 360
						},
						"m_scaleX": 1,
						"m_scaleY": 1,
						"m_rotationAngle": 0,
						"m_isArtFlipped": false,
						"m_rotationRate": -2
					},
					{
						"m_eventType": "island",
						"m_imageID": 11,
						"m_parallaxLayer": 4,
						"m_drawLayer": 0,
						"m_position": {
							"x": 8507.239258000003,
							"y": 372
						},
						"m_scaleX": 0.9,
						"m_scaleY": 0.9,
						"m_rotationAngle": 0,
						"m_isArtFlipped": false,
						"m_rotationRate": 5
					},
					{
						"m_eventType": "island",
						"m_imageID": 12,
						"m_parallaxLayer": 4,
						"m_drawLayer": 0,
						"m_position": {
							"x": 9026.223633,
							"y": 139
						},
						"m_scaleX": 0.8,
						"m_scaleY": 0.8,
						"m_rotationAngle": 0,
						"m_isArtFlipped": false,
						"m_rotationRate": 2
					},
					{
						"m_eventType": "island",
						"m_imageID": 100,
						"m_parallaxLayer": 2,
						"m_drawLayer": 0,
						"m_position": {
							"x": 9160.259766000001,
							"y": 239
						},
						"m_scaleX": 0.8,
						"m_scaleY": 0.8,
						"m_rotationAngle": 0,
						"m_isArtFlipped": true,
						"m_rotationRate": 0
					},
					{
						"m_eventType": "island",
						"m_imageID": 101,
						"m_parallaxLayer": 0,
						"m_drawLayer": 0,
						"m_position": {
							"x": 6742.968749999999,
							"y": 469
						},
						"m_scaleX": 1,
						"m_scaleY": 1,
						"m_rotationAngle": 325,
						"m_isArtFlipped": false,
						"m_rotationRate": 0
					},
					{
						"m_eventType": "island",
						"m_imageID": 101,
						"m_parallaxLayer": 0,
						"m_drawLayer": 0,
						"m_position": {
							"x": 6705.468749999999,
							"y": 463
						},
						"m_scaleX": 1,
						"m_scaleY": 1,
						"m_rotationAngle": 350,
						"m_isArtFlipped": false,
						"m_rotationRate": 0
					},
					{
						"m_eventType": "island",
						"m_imageID": 101,
						"m_parallaxLayer": 0,
						"m_drawLayer": 0,
						"m_position": {
							"x": 6773.437499999999,
							"y": 465
						},
						"m_scaleX": 1,
						"m_scaleY": 1,
						"m_rotationAngle": 285,
						"m_isArtFlipped": false,
						"m_rotationRate": 0
					},
					{
						"m_eventType": "island",
						"m_imageID": 101,
						"m_parallaxLayer": 0,
						"m_drawLayer": 0,
						"m_position": {
							"x": 6910.156250000001,
							"y": 369
						},
						"m_scaleX": 1,
						"m_scaleY": 1,
						"m_rotationAngle": 0,
						"m_isArtFlipped": false,
						"m_rotationRate": 0
					},
					{
						"m_eventType": "island",
						"m_imageID": 101,
						"m_parallaxLayer": 0,
						"m_drawLayer": 0,
						"m_position": {
							"x": 7035.937499999999,
							"y": 342
						},
						"m_scaleX": 1,
						"m_scaleY": 1,
						"m_rotationAngle": 335,
						"m_isArtFlipped": false,
						"m_rotationRate": 0
					},
					{
						"m_eventType": "island",
						"m_imageID": 101,
						"m_parallaxLayer": 0,
						"m_drawLayer": 0,
						"m_position": {
							"x": 6967.1875,
							"y": 340
						},
						"m_scaleX": 1,
						"m_scaleY": 1,
						"m_rotationAngle": 350,
						"m_isArtFlipped": false,
						"m_rotationRate": 0
					},
					{
						"m_eventType": "island",
						"m_imageID": 101,
						"m_parallaxLayer": 0,
						"m_drawLayer": 0,
						"m_position": {
							"x": 7003.90625,
							"y": 346
						},
						"m_scaleX": 1,
						"m_scaleY": 1,
						"m_rotationAngle": 275,
						"m_isArtFlipped": false,
						"m_rotationRate": 0
					},
					{
						"m_eventType": "island",
						"m_imageID": 101,
						"m_parallaxLayer": 0,
						"m_drawLayer": 0,
						"m_position": {
							"x": 7523.437499999999,
							"y": 343
						},
						"m_scaleX": 1,
						"m_scaleY": 1,
						"m_rotationAngle": 350,
						"m_isArtFlipped": false,
						"m_rotationRate": 0
					},
					{
						"m_eventType": "island",
						"m_imageID": 101,
						"m_parallaxLayer": 0,
						"m_drawLayer": 0,
						"m_position": {
							"x": 7555.468749999999,
							"y": 350
						},
						"m_scaleX": 1,
						"m_scaleY": 1,
						"m_rotationAngle": 335,
						"m_isArtFlipped": false,
						"m_rotationRate": 0
					},
					{
						"m_eventType": "island",
						"m_imageID": 101,
						"m_parallaxLayer": 0,
						"m_drawLayer": 0,
						"m_position": {
							"x": 7589.062500000001,
							"y": 346
						},
						"m_scaleX": 1,
						"m_scaleY": 1,
						"m_rotationAngle": 335,
						"m_isArtFlipped": false,
						"m_rotationRate": 0
					},
					{
						"m_eventType": "island",
						"m_imageID": 101,
						"m_parallaxLayer": 0,
						"m_drawLayer": 0,
						"m_position": {
							"x": 7653.125000000001,
							"y": 369
						},
						"m_scaleX": 1,
						"m_scaleY": 1,
						"m_rotationAngle": 0,
						"m_isArtFlipped": false,
						"m_rotationRate": 0
					},
					{
						"m_eventType": "island",
						"m_imageID": 101,
						"m_parallaxLayer": 0,
						"m_drawLayer": 0,
						"m_position": {
							"x": 7790.625000000001,
							"y": 459
						},
						"m_scaleX": 1,
						"m_scaleY": 1,
						"m_rotationAngle": 350,
						"m_isArtFlipped": false,
						"m_rotationRate": 0
					},
					{
						"m_eventType": "island",
						"m_imageID": 101,
						"m_parallaxLayer": 0,
						"m_drawLayer": 0,
						"m_position": {
							"x": 7827.343749999999,
							"y": 465
						},
						"m_scaleX": 1,
						"m_scaleY": 1,
						"m_rotationAngle": 30,
						"m_isArtFlipped": false,
						"m_rotationRate": 0
					},
					{
						"m_eventType": "island",
						"m_imageID": 101,
						"m_parallaxLayer": 0,
						"m_drawLayer": 0,
						"m_position": {
							"x": 7860.937499999999,
							"y": 461
						},
						"m_scaleX": 1,
						"m_scaleY": 1,
						"m_rotationAngle": 5,
						"m_isArtFlipped": false,
						"m_rotationRate": 0
					},
					{
						"m_eventType": "island",
						"m_imageID": 101,
						"m_parallaxLayer": 0,
						"m_drawLayer": 0,
						"m_position": {
							"x": 7994.53125,
							"y": 365
						},
						"m_scaleX": 1,
						"m_scaleY": 1,
						"m_rotationAngle": 0,
						"m_isArtFlipped": false,
						"m_rotationRate": 0
					},
					{
						"m_eventType": "island",
						"m_imageID": 101,
						"m_parallaxLayer": 0,
						"m_drawLayer": 0,
						"m_position": {
							"x": 8112.5,
							"y": 300
						},
						"m_scaleX": 1,
						"m_scaleY": 1,
						"m_rotationAngle": 0,
						"m_isArtFlipped": false,
						"m_rotationRate": 0
					},
					{
						"m_eventType": "island",
						"m_imageID": 101,
						"m_parallaxLayer": 0,
						"m_drawLayer": 0,
						"m_position": {
							"x": 8162.5,
							"y": 271
						},
						"m_scaleX": 1,
						"m_scaleY": 1,
						"m_rotationAngle": 350,
						"m_isArtFlipped": false,
						"m_rotationRate": 0
					},
					{
						"m_eventType": "island",
						"m_imageID": 101,
						"m_parallaxLayer": 0,
						"m_drawLayer": 0,
						"m_position": {
							"x": 8199.219000000001,
							"y": 278
						},
						"m_scaleX": 1,
						"m_scaleY": 1,
						"m_rotationAngle": 325,
						"m_isArtFlipped": false,
						"m_rotationRate": 0
					},
					{
						"m_eventType": "island",
						"m_imageID": 101,
						"m_parallaxLayer": 0,
						"m_drawLayer": 0,
						"m_position": {
							"x": 8232.8125,
							"y": 275
						},
						"m_scaleX": 1,
						"m_scaleY": 1,
						"m_rotationAngle": 5,
						"m_isArtFlipped": false,
						"m_rotationRate": 0
					},
					{
						"m_eventType": "island",
						"m_imageID": 101,
						"m_parallaxLayer": 0,
						"m_drawLayer": 0,
						"m_position": {
							"x": 8289.844000000001,
							"y": 300
						},
						"m_scaleX": 1,
						"m_scaleY": 1,
						"m_rotationAngle": 0,
						"m_isArtFlipped": false,
						"m_rotationRate": 0
					},
					{
						"m_eventType": "island",
						"m_imageID": 101,
						"m_parallaxLayer": 0,
						"m_drawLayer": 0,
						"m_position": {
							"x": 8409.374999999998,
							"y": 369
						},
						"m_scaleX": 1,
						"m_scaleY": 1,
						"m_rotationAngle": 0,
						"m_isArtFlipped": false,
						"m_rotationRate": 0
					},
					{
						"m_eventType": "island",
						"m_imageID": 101,
						"m_parallaxLayer": 0,
						"m_drawLayer": 0,
						"m_position": {
							"x": 8542.969,
							"y": 460
						},
						"m_scaleX": 1,
						"m_scaleY": 1,
						"m_rotationAngle": 350,
						"m_isArtFlipped": false,
						"m_rotationRate": 0
					},
					{
						"m_eventType": "island",
						"m_imageID": 101,
						"m_parallaxLayer": 0,
						"m_drawLayer": 0,
						"m_position": {
							"x": 8581.25,
							"y": 467
						},
						"m_scaleX": 1,
						"m_scaleY": 1,
						"m_rotationAngle": 55,
						"m_isArtFlipped": false,
						"m_rotationRate": 0
					},
					{
						"m_eventType": "island",
						"m_imageID": 101,
						"m_parallaxLayer": 0,
						"m_drawLayer": 0,
						"m_position": {
							"x": 8614.844000000001,
							"y": 461
						},
						"m_scaleX": 1,
						"m_scaleY": 1,
						"m_rotationAngle": 5,
						"m_isArtFlipped": false,
						"m_rotationRate": 0
					},
					{
						"m_eventType": "island",
						"m_imageID": 101,
						"m_parallaxLayer": 0,
						"m_drawLayer": 0,
						"m_position": {
							"x": 8752.344000000001,
							"y": 367
						},
						"m_scaleX": 1,
						"m_scaleY": 1,
						"m_rotationAngle": 0,
						"m_isArtFlipped": false,
						"m_rotationRate": 0
					},
					{
						"m_eventType": "island",
						"m_imageID": 101,
						"m_parallaxLayer": 0,
						"m_drawLayer": 0,
						"m_position": {
							"x": 8870.3125,
							"y": 300
						},
						"m_scaleX": 1,
						"m_scaleY": 1,
						"m_rotationAngle": 0,
						"m_isArtFlipped": false,
						"m_rotationRate": 0
					},
					{
						"m_eventType": "island",
						"m_imageID": 101,
						"m_parallaxLayer": 0,
						"m_drawLayer": 0,
						"m_position": {
							"x": 8924.219000000001,
							"y": 273
						},
						"m_scaleX": 1,
						"m_scaleY": 1,
						"m_rotationAngle": 350,
						"m_isArtFlipped": false,
						"m_rotationRate": 0
					},
					{
						"m_eventType": "island",
						"m_imageID": 101,
						"m_parallaxLayer": 0,
						"m_drawLayer": 0,
						"m_position": {
							"x": 8962.5,
							"y": 280
						},
						"m_scaleX": 1,
						"m_scaleY": 1,
						"m_rotationAngle": 325,
						"m_isArtFlipped": false,
						"m_rotationRate": 0
					},
					{
						"m_eventType": "island",
						"m_imageID": 101,
						"m_parallaxLayer": 0,
						"m_drawLayer": 0,
						"m_position": {
							"x": 8995.3125,
							"y": 276
						},
						"m_scaleX": 1,
						"m_scaleY": 1,
						"m_rotationAngle": 5,
						"m_isArtFlipped": false,
						"m_rotationRate": 0
					},
					{
						"m_eventType": "island",
						"m_imageID": 101,
						"m_parallaxLayer": 0,
						"m_drawLayer": 0,
						"m_position": {
							"x": 9053.905999999999,
							"y": 302
						},
						"m_scaleX": 1,
						"m_scaleY": 1,
						"m_rotationAngle": 0,
						"m_isArtFlipped": false,
						"m_rotationRate": 0
					},
					{
						"m_eventType": "island",
						"m_imageID": 101,
						"m_parallaxLayer": 0,
						"m_drawLayer": 0,
						"m_position": {
							"x": 9171.874999999998,
							"y": 367
						},
						"m_scaleX": 1,
						"m_scaleY": 1,
						"m_rotationAngle": 0,
						"m_isArtFlipped": false,
						"m_rotationRate": 0
					},
					{
						"m_eventType": "island",
						"m_imageID": 101,
						"m_parallaxLayer": 0,
						"m_drawLayer": 0,
						"m_position": {
							"x": 9307.031,
							"y": 463
						},
						"m_scaleX": 1,
						"m_scaleY": 1,
						"m_rotationAngle": 350,
						"m_isArtFlipped": false,
						"m_rotationRate": 0
					},
					{
						"m_eventType": "island",
						"m_imageID": 101,
						"m_parallaxLayer": 0,
						"m_drawLayer": 0,
						"m_position": {
							"x": 9342.969,
							"y": 469
						},
						"m_scaleX": 1,
						"m_scaleY": 1,
						"m_rotationAngle": 325,
						"m_isArtFlipped": false,
						"m_rotationRate": 0
					},
					{
						"m_eventType": "island",
						"m_imageID": 101,
						"m_parallaxLayer": 0,
						"m_drawLayer": 0,
						"m_position": {
							"x": 9377.344000000001,
							"y": 464
						},
						"m_scaleX": 1,
						"m_scaleY": 1,
						"m_rotationAngle": 5,
						"m_isArtFlipped": false,
						"m_rotationRate": 0
					},
					{
						"m_eventType": "island",
						"m_imageID": 101,
						"m_parallaxLayer": 0,
						"m_drawLayer": 0,
						"m_position": {
							"x": 9509.374999999998,
							"y": 372
						},
						"m_scaleX": 1,
						"m_scaleY": 1,
						"m_rotationAngle": 0,
						"m_isArtFlipped": false,
						"m_rotationRate": 0
					},
					{
						"m_eventType": "island",
						"m_imageID": 101,
						"m_parallaxLayer": 0,
						"m_drawLayer": 0,
						"m_position": {
							"x": 9626.5625,
							"y": 305
						},
						"m_scaleX": 1,
						"m_scaleY": 1,
						"m_rotationAngle": 0,
						"m_isArtFlipped": false,
						"m_rotationRate": 0
					},
					{
						"m_eventType": "island",
						"m_imageID": 101,
						"m_parallaxLayer": 0,
						"m_drawLayer": 0,
						"m_position": {
							"x": 9682.031,
							"y": 278
						},
						"m_scaleX": 1,
						"m_scaleY": 1,
						"m_rotationAngle": 350,
						"m_isArtFlipped": false,
						"m_rotationRate": 0
					},
					{
						"m_eventType": "island",
						"m_imageID": 101,
						"m_parallaxLayer": 0,
						"m_drawLayer": 0,
						"m_position": {
							"x": 9718.75,
							"y": 286
						},
						"m_scaleX": 1,
						"m_scaleY": 1,
						"m_rotationAngle": 325,
						"m_isArtFlipped": false,
						"m_rotationRate": 0
					},
					{
						"m_eventType": "island",
						"m_imageID": 101,
						"m_parallaxLayer": 0,
						"m_drawLayer": 0,
						"m_position": {
							"x": 9752.344000000001,
							"y": 282
						},
						"m_scaleX": 1,
						"m_scaleY": 1,
						"m_rotationAngle": 5,
						"m_isArtFlipped": false,
						"m_rotationRate": 0
					},
					{
						"m_eventType": "island",
						"m_imageID": 101,
						"m_parallaxLayer": 0,
						"m_drawLayer": 0,
						"m_position": {
							"x": 9810.155999999999,
							"y": 310
						},
						"m_scaleX": 1,
						"m_scaleY": 1,
						"m_rotationAngle": 0,
						"m_isArtFlipped": false,
						"m_rotationRate": 0
					},
					{
						"m_eventType": "island",
						"m_imageID": 101,
						"m_parallaxLayer": 0,
						"m_drawLayer": 0,
						"m_position": {
							"x": 9928.905999999999,
							"y": 375
						},
						"m_scaleX": 1,
						"m_scaleY": 1,
						"m_rotationAngle": 0,
						"m_isArtFlipped": false,
						"m_rotationRate": 0
					},
					{
						"m_eventType": "island",
						"m_imageID": 101,
						"m_parallaxLayer": 0,
						"m_drawLayer": 0,
						"m_position": {
							"x": 10060.156299999999,
							"y": 471
						},
						"m_scaleX": 1,
						"m_scaleY": 1,
						"m_rotationAngle": 350,
						"m_isArtFlipped": false,
						"m_rotationRate": 0
					},
					{
						"m_eventType": "island",
						"m_imageID": 101,
						"m_parallaxLayer": 0,
						"m_drawLayer": 0,
						"m_position": {
							"x": 10097.656299999999,
							"y": 478
						},
						"m_scaleX": 1,
						"m_scaleY": 1,
						"m_rotationAngle": 325,
						"m_isArtFlipped": false,
						"m_rotationRate": 0
					},
					{
						"m_eventType": "island",
						"m_imageID": 101,
						"m_parallaxLayer": 0,
						"m_drawLayer": 0,
						"m_position": {
							"x": 10132.0313,
							"y": 474
						},
						"m_scaleX": 1,
						"m_scaleY": 1,
						"m_rotationAngle": 5,
						"m_isArtFlipped": false,
						"m_rotationRate": 0
					},
					{
						"m_eventType": "island",
						"m_imageID": 101,
						"m_parallaxLayer": 0,
						"m_drawLayer": 0,
						"m_position": {
							"x": 10260.9375,
							"y": 375
						},
						"m_scaleX": 1,
						"m_scaleY": 1,
						"m_rotationAngle": 0,
						"m_isArtFlipped": false,
						"m_rotationRate": 0
					},
					{
						"m_eventType": "island",
						"m_imageID": 101,
						"m_parallaxLayer": 0,
						"m_drawLayer": 0,
						"m_position": {
							"x": 10379.6875,
							"y": 306
						},
						"m_scaleX": 1,
						"m_scaleY": 1,
						"m_rotationAngle": 0,
						"m_isArtFlipped": false,
						"m_rotationRate": 0
					},
					{
						"m_eventType": "island",
						"m_imageID": 101,
						"m_parallaxLayer": 0,
						"m_drawLayer": 0,
						"m_position": {
							"x": 10430.468799999999,
							"y": 277
						},
						"m_scaleX": 1,
						"m_scaleY": 1,
						"m_rotationAngle": 350,
						"m_isArtFlipped": false,
						"m_rotationRate": 0
					},
					{
						"m_eventType": "island",
						"m_imageID": 101,
						"m_parallaxLayer": 0,
						"m_drawLayer": 0,
						"m_position": {
							"x": 10468.75,
							"y": 285
						},
						"m_scaleX": 1,
						"m_scaleY": 1,
						"m_rotationAngle": 325,
						"m_isArtFlipped": false,
						"m_rotationRate": 0
					},
					{
						"m_eventType": "island",
						"m_imageID": 101,
						"m_parallaxLayer": 0,
						"m_drawLayer": 0,
						"m_position": {
							"x": 10501.5625,
							"y": 279
						},
						"m_scaleX": 1,
						"m_scaleY": 1,
						"m_rotationAngle": 5,
						"m_isArtFlipped": false,
						"m_rotationRate": 0
					},
					{
						"m_eventType": "island",
						"m_imageID": 9,
						"m_parallaxLayer": 9,
						"m_drawLayer": 0,
						"m_position": {
							"x": 5776.63916,
							"y": 139
						},
						"m_scaleX": 0.8,
						"m_scaleY": 0.8,
						"m_rotationAngle": 0,
						"m_isArtFlipped": false,
						"m_rotationRate": -1
					},
					{
						"m_eventType": "island",
						"m_imageID": 9,
						"m_parallaxLayer": 9,
						"m_drawLayer": 0,
						"m_position": {
							"x": 5524.998046999999,
							"y": 117
						},
						"m_scaleX": 0.8,
						"m_scaleY": 0.8,
						"m_rotationAngle": 0,
						"m_isArtFlipped": true,
						"m_rotationRate": 1
					},
					{
						"m_eventType": "island",
						"m_imageID": 112,
						"m_parallaxLayer": 3,
						"m_drawLayer": 0,
						"m_position": {
							"x": 7756.796386999999,
							"y": 309
						},
						"m_scaleX": 0.8,
						"m_scaleY": 0.8,
						"m_rotationAngle": 0,
						"m_isArtFlipped": false,
						"m_rotationRate": 0
					},
					{
						"m_eventType": "island",
						"m_imageID": 19,
						"m_parallaxLayer": 4,
						"m_drawLayer": 0,
						"m_position": {
							"x": 8475.208008000001,
							"y": 185
						},
						"m_scaleX": 1,
						"m_scaleY": 1,
						"m_rotationAngle": 0,
						"m_isArtFlipped": false,
						"m_rotationRate": -3
					},
					{
						"m_eventType": "island",
						"m_imageID": 20,
						"m_parallaxLayer": 4,
						"m_drawLayer": 0,
						"m_position": {
							"x": 8477.083008000001,
							"y": 215
						},
						"m_scaleX": 1,
						"m_scaleY": 1,
						"m_rotationAngle": 350,
						"m_isArtFlipped": false,
						"m_rotationRate": 0
					},
					{
						"m_eventType": "island",
						"m_imageID": 103,
						"m_parallaxLayer": 2,
						"m_drawLayer": 0,
						"m_position": {
							"x": 5786.197753999999,
							"y": 189
						},
						"m_scaleX": 1.6,
						"m_scaleY": 1.6,
						"m_rotationAngle": 0,
						"m_isArtFlipped": false,
						"m_rotationRate": 0
					},
					{
						"m_eventType": "island",
						"m_imageID": 103,
						"m_parallaxLayer": 2,
						"m_drawLayer": 0,
						"m_position": {
							"x": 5533.229004,
							"y": 281
						},
						"m_scaleX": 1.5,
						"m_scaleY": 1.5,
						"m_rotationAngle": 0,
						"m_isArtFlipped": false,
						"m_rotationRate": 0
					},
					{
						"m_eventType": "island",
						"m_imageID": 103,
						"m_parallaxLayer": 2,
						"m_drawLayer": 0,
						"m_position": {
							"x": 5637.447266,
							"y": 132
						},
						"m_scaleX": 1.4,
						"m_scaleY": 1.4,
						"m_rotationAngle": 0,
						"m_isArtFlipped": false,
						"m_rotationRate": 0
					},
					{
						"m_eventType": "island",
						"m_imageID": 103,
						"m_parallaxLayer": 2,
						"m_drawLayer": 0,
						"m_position": {
							"x": 5852.604004,
							"y": 345
						},
						"m_scaleX": 1,
						"m_scaleY": 1,
						"m_rotationAngle": 0,
						"m_isArtFlipped": false,
						"m_rotationRate": 0
					},
					{
						"m_eventType": "island",
						"m_imageID": 111,
						"m_parallaxLayer": 0,
						"m_drawLayer": 0,
						"m_position": {
							"x": 5801.562500000001,
							"y": 389
						},
						"m_scaleX": 0.9,
						"m_scaleY": 0.9,
						"m_rotationAngle": 0,
						"m_isArtFlipped": false,
						"m_rotationRate": 0
					},
					{
						"m_eventType": "island",
						"m_imageID": 11,
						"m_parallaxLayer": 3,
						"m_drawLayer": -1,
						"m_position": {
							"x": 8688.828,
							"y": 340
						},
						"m_scaleX": 1,
						"m_scaleY": 1,
						"m_rotationAngle": 0,
						"m_isArtFlipped": false,
						"m_rotationRate": -8
					},
					{
						"m_eventType": "island",
						"m_imageID": 11,
						"m_parallaxLayer": 1,
						"m_drawLayer": -1,
						"m_position": {
							"x": 9381.692383,
							"y": 141
						},
						"m_scaleX": 0.4,
						"m_scaleY": 0.4,
						"m_rotationAngle": 0,
						"m_isArtFlipped": false,
						"m_rotationRate": 13
					},
					{
						"m_eventType": "island",
						"m_imageID": 109,
						"m_parallaxLayer": 0,
						"m_drawLayer": -3,
						"m_position": {
							"x": 6051.562500000001,
							"y": 330
						},
						"m_scaleX": 0.9,
						"m_scaleY": 0.9,
						"m_rotationAngle": 0,
						"m_isArtFlipped": false,
						"m_rotationRate": 0
					},
					{
						"m_eventType": "island",
						"m_imageID": 11,
						"m_parallaxLayer": 0,
						"m_drawLayer": 0,
						"m_position": {
							"x": 11140.625,
							"y": 364
						},
						"m_scaleX": 0.6000000000000001,
						"m_scaleY": 0.6000000000000001,
						"m_rotationAngle": 0,
						"m_isArtFlipped": false,
						"m_rotationRate": -13
					},
					{
						"m_eventType": "island",
						"m_imageID": 11,
						"m_parallaxLayer": 4,
						"m_drawLayer": 0,
						"m_position": {
							"x": 7931.45752,
							"y": 182
						},
						"m_scaleX": 1,
						"m_scaleY": 1,
						"m_rotationAngle": 0,
						"m_isArtFlipped": false,
						"m_rotationRate": 9
					},
					{
						"m_eventType": "island",
						"m_imageID": 5,
						"m_parallaxLayer": 0,
						"m_drawLayer": 1,
						"m_position": {
							"x": 7281.25,
							"y": 349
						},
						"m_scaleX": 1.08,
						"m_scaleY": 1.08,
						"m_rotationAngle": 0,
						"m_isArtFlipped": false,
						"m_rotationRate": 0
					},
					{
						"m_eventType": "island",
						"m_imageID": 102,
						"m_parallaxLayer": 0,
						"m_drawLayer": -1,
						"m_position": {
							"x": 7271.875,
							"y": 504
						},
						"m_scaleX": 1,
						"m_scaleY": 1,
						"m_rotationAngle": 0,
						"m_isArtFlipped": false,
						"m_rotationRate": 0
					},
					{
						"m_eventType": "island",
						"m_imageID": 101,
						"m_parallaxLayer": 0,
						"m_drawLayer": 3,
						"m_position": {
							"x": 7324.218749999999,
							"y": 468
						},
						"m_scaleX": 1,
						"m_scaleY": 1,
						"m_rotationAngle": 0,
						"m_isArtFlipped": false,
						"m_rotationRate": 0
					},
					{
						"m_eventType": "island",
						"m_imageID": 101,
						"m_parallaxLayer": 0,
						"m_drawLayer": 3,
						"m_position": {
							"x": 7240.625000000001,
							"y": 464
						},
						"m_scaleX": 1,
						"m_scaleY": 1,
						"m_rotationAngle": 0,
						"m_isArtFlipped": false,
						"m_rotationRate": 0
					},
					{
						"m_eventType": "island",
						"m_imageID": 101,
						"m_parallaxLayer": 0,
						"m_drawLayer": 3,
						"m_position": {
							"x": 7280.468749999999,
							"y": 472
						},
						"m_scaleX": 1,
						"m_scaleY": 1,
						"m_rotationAngle": 0,
						"m_isArtFlipped": false,
						"m_rotationRate": 0
					},
					{
						"m_eventType": "island",
						"m_imageID": 101,
						"m_parallaxLayer": 0,
						"m_drawLayer": 0,
						"m_position": {
							"x": 11049.5,
							"y": 271
						},
						"m_scaleX": 1,
						"m_scaleY": 1,
						"m_rotationAngle": 350,
						"m_isArtFlipped": false,
						"m_rotationRate": 0
					},
					{
						"m_eventType": "island",
						"m_imageID": 102,
						"m_parallaxLayer": 0,
						"m_drawLayer": -3,
						"m_position": {
							"x": 11077.625,
							"y": 303
						},
						"m_scaleX": 1,
						"m_scaleY": 1,
						"m_rotationAngle": 0,
						"m_isArtFlipped": false,
						"m_rotationRate": 0
					},
					{
						"m_eventType": "island",
						"m_imageID": 5,
						"m_parallaxLayer": 0,
						"m_drawLayer": 0,
						"m_position": {
							"x": 11084.656299999999,
							"y": 163
						},
						"m_scaleX": 1,
						"m_scaleY": 1,
						"m_rotationAngle": 0,
						"m_isArtFlipped": false,
						"m_rotationRate": 0
					},
					{
						"m_eventType": "island",
						"m_imageID": 101,
						"m_parallaxLayer": 0,
						"m_drawLayer": 0,
						"m_position": {
							"x": 11086.2188,
							"y": 278
						},
						"m_scaleX": 1,
						"m_scaleY": 1,
						"m_rotationAngle": 325,
						"m_isArtFlipped": false,
						"m_rotationRate": 0
					},
					{
						"m_eventType": "island",
						"m_imageID": 101,
						"m_parallaxLayer": 0,
						"m_drawLayer": 0,
						"m_position": {
							"x": 11119.8125,
							"y": 275
						},
						"m_scaleX": 1,
						"m_scaleY": 1,
						"m_rotationAngle": 5,
						"m_isArtFlipped": false,
						"m_rotationRate": 0
					},
					{
						"m_eventType": "island",
						"m_imageID": 7,
						"m_parallaxLayer": 0,
						"m_drawLayer": 2,
						"m_position": {
							"x": 11147.9375,
							"y": 221
						},
						"m_scaleX": 1,
						"m_scaleY": 1,
						"m_rotationAngle": 0,
						"m_isArtFlipped": false,
						"m_rotationRate": 0
					},
					{
						"m_eventType": "island",
						"m_imageID": 101,
						"m_parallaxLayer": 0,
						"m_drawLayer": 0,
						"m_position": {
							"x": 11176.8438,
							"y": 300
						},
						"m_scaleX": 1,
						"m_scaleY": 1,
						"m_rotationAngle": 0,
						"m_isArtFlipped": false,
						"m_rotationRate": 0
					},
					{
						"m_eventType": "island",
						"m_imageID": 4,
						"m_parallaxLayer": 0,
						"m_drawLayer": 0,
						"m_position": {
							"x": 11215.906299999999,
							"y": 227
						},
						"m_scaleX": 1,
						"m_scaleY": 1,
						"m_rotationAngle": 0,
						"m_isArtFlipped": true,
						"m_rotationRate": 0
					},
					{
						"m_eventType": "island",
						"m_imageID": 101,
						"m_parallaxLayer": 0,
						"m_drawLayer": 0,
						"m_position": {
							"x": 11296.374999999998,
							"y": 369
						},
						"m_scaleX": 1,
						"m_scaleY": 1,
						"m_rotationAngle": 0,
						"m_isArtFlipped": false,
						"m_rotationRate": 0
					},
					{
						"m_eventType": "island",
						"m_imageID": 4,
						"m_parallaxLayer": 0,
						"m_drawLayer": 0,
						"m_position": {
							"x": 11334.656299999999,
							"y": 295
						},
						"m_scaleX": 1,
						"m_scaleY": 1,
						"m_rotationAngle": 0,
						"m_isArtFlipped": true,
						"m_rotationRate": 0
					},
					{
						"m_eventType": "island",
						"m_imageID": 19,
						"m_parallaxLayer": 4,
						"m_drawLayer": 0,
						"m_position": {
							"x": 11362.20801,
							"y": 185
						},
						"m_scaleX": 1,
						"m_scaleY": 1,
						"m_rotationAngle": 0,
						"m_isArtFlipped": false,
						"m_rotationRate": -3
					},
					{
						"m_eventType": "island",
						"m_imageID": 20,
						"m_parallaxLayer": 4,
						"m_drawLayer": 0,
						"m_position": {
							"x": 11364.08301,
							"y": 215
						},
						"m_scaleX": 1,
						"m_scaleY": 1,
						"m_rotationAngle": 350,
						"m_isArtFlipped": false,
						"m_rotationRate": 0
					},
					{
						"m_eventType": "island",
						"m_imageID": 11,
						"m_parallaxLayer": 4,
						"m_drawLayer": 0,
						"m_position": {
							"x": 11394.239260000002,
							"y": 372
						},
						"m_scaleX": 0.9,
						"m_scaleY": 0.9,
						"m_rotationAngle": 0,
						"m_isArtFlipped": false,
						"m_rotationRate": 5
					},
					{
						"m_eventType": "island",
						"m_imageID": 6,
						"m_parallaxLayer": 0,
						"m_drawLayer": 2,
						"m_position": {
							"x": 11394.8125,
							"y": 347
						},
						"m_scaleX": 1,
						"m_scaleY": 1,
						"m_rotationAngle": 0,
						"m_isArtFlipped": true,
						"m_rotationRate": 0
					},
					{
						"m_eventType": "island",
						"m_imageID": 101,
						"m_parallaxLayer": 0,
						"m_drawLayer": 0,
						"m_position": {
							"x": 11429.968799999999,
							"y": 460
						},
						"m_scaleX": 1,
						"m_scaleY": 1,
						"m_rotationAngle": 350,
						"m_isArtFlipped": false,
						"m_rotationRate": 0
					},
					{
						"m_eventType": "island",
						"m_imageID": 102,
						"m_parallaxLayer": 0,
						"m_drawLayer": -3,
						"m_position": {
							"x": 11458.874999999998,
							"y": 487
						},
						"m_scaleX": 1,
						"m_scaleY": 1,
						"m_rotationAngle": 0,
						"m_isArtFlipped": false,
						"m_rotationRate": 0
					},
					{
						"m_eventType": "island",
						"m_imageID": 5,
						"m_parallaxLayer": 0,
						"m_drawLayer": 0,
						"m_position": {
							"x": 11466.6875,
							"y": 352
						},
						"m_scaleX": 1,
						"m_scaleY": 1,
						"m_rotationAngle": 0,
						"m_isArtFlipped": false,
						"m_rotationRate": 0
					},
					{
						"m_eventType": "island",
						"m_imageID": 101,
						"m_parallaxLayer": 0,
						"m_drawLayer": 0,
						"m_position": {
							"x": 11468.25,
							"y": 467
						},
						"m_scaleX": 1,
						"m_scaleY": 1,
						"m_rotationAngle": 55,
						"m_isArtFlipped": false,
						"m_rotationRate": 0
					},
					{
						"m_eventType": "island",
						"m_imageID": 101,
						"m_parallaxLayer": 0,
						"m_drawLayer": 0,
						"m_position": {
							"x": 11501.8438,
							"y": 461
						},
						"m_scaleX": 1,
						"m_scaleY": 1,
						"m_rotationAngle": 5,
						"m_isArtFlipped": false,
						"m_rotationRate": 0
					},
					{
						"m_eventType": "island",
						"m_imageID": 6,
						"m_parallaxLayer": 0,
						"m_drawLayer": 2,
						"m_position": {
							"x": 11531.5313,
							"y": 350
						},
						"m_scaleX": 1,
						"m_scaleY": 1,
						"m_rotationAngle": 0,
						"m_isArtFlipped": false,
						"m_rotationRate": 0
					},
					{
						"m_eventType": "island",
						"m_imageID": 11,
						"m_parallaxLayer": 3,
						"m_drawLayer": -1,
						"m_position": {
							"x": 11575.828129999987,
							"y": 340
						},
						"m_scaleX": 1,
						"m_scaleY": 1,
						"m_rotationAngle": 0,
						"m_isArtFlipped": false,
						"m_rotationRate": -8
					},
					{
						"m_eventType": "island",
						"m_imageID": 4,
						"m_parallaxLayer": 0,
						"m_drawLayer": 0,
						"m_position": {
							"x": 11600.2813,
							"y": 293
						},
						"m_scaleX": 1,
						"m_scaleY": 1,
						"m_rotationAngle": 0,
						"m_isArtFlipped": false,
						"m_rotationRate": 0
					},
					{
						"m_eventType": "island",
						"m_imageID": 13,
						"m_parallaxLayer": 0,
						"m_drawLayer": 0,
						"m_position": {
							"x": 11602.625,
							"y": 360
						},
						"m_scaleX": 1,
						"m_scaleY": 1,
						"m_rotationAngle": 0,
						"m_isArtFlipped": false,
						"m_rotationRate": 0
					},
					{
						"m_eventType": "island",
						"m_imageID": 101,
						"m_parallaxLayer": 0,
						"m_drawLayer": 0,
						"m_position": {
							"x": 11639.3438,
							"y": 367
						},
						"m_scaleX": 1,
						"m_scaleY": 1,
						"m_rotationAngle": 0,
						"m_isArtFlipped": false,
						"m_rotationRate": 0
					},
					{
						"m_eventType": "island",
						"m_imageID": 4,
						"m_parallaxLayer": 0,
						"m_drawLayer": 0,
						"m_position": {
							"x": 11719.8125,
							"y": 226
						},
						"m_scaleX": 1,
						"m_scaleY": 1,
						"m_rotationAngle": 0,
						"m_isArtFlipped": false,
						"m_rotationRate": 0
					},
					{
						"m_eventType": "island",
						"m_imageID": 101,
						"m_parallaxLayer": 0,
						"m_drawLayer": 0,
						"m_position": {
							"x": 11757.3125,
							"y": 300
						},
						"m_scaleX": 1,
						"m_scaleY": 1,
						"m_rotationAngle": 0,
						"m_isArtFlipped": false,
						"m_rotationRate": 0
					},
					{
						"m_eventType": "island",
						"m_imageID": 7,
						"m_parallaxLayer": 0,
						"m_drawLayer": 2,
						"m_position": {
							"x": 11785.4375,
							"y": 221
						},
						"m_scaleX": 1,
						"m_scaleY": 1,
						"m_rotationAngle": 0,
						"m_isArtFlipped": true,
						"m_rotationRate": 0
					},
					{
						"m_eventType": "island",
						"m_imageID": 101,
						"m_parallaxLayer": 0,
						"m_drawLayer": 0,
						"m_position": {
							"x": 11811.2188,
							"y": 273
						},
						"m_scaleX": 1,
						"m_scaleY": 1,
						"m_rotationAngle": 350,
						"m_isArtFlipped": false,
						"m_rotationRate": 0
					},
					{
						"m_eventType": "island",
						"m_imageID": 102,
						"m_parallaxLayer": 0,
						"m_drawLayer": -3,
						"m_position": {
							"x": 11837,
							"y": 299
						},
						"m_scaleX": 1,
						"m_scaleY": 1,
						"m_rotationAngle": 0,
						"m_isArtFlipped": false,
						"m_rotationRate": 0
					},
					{
						"m_eventType": "island",
						"m_imageID": 5,
						"m_parallaxLayer": 0,
						"m_drawLayer": 0,
						"m_position": {
							"x": 11847.9375,
							"y": 165
						},
						"m_scaleX": 1,
						"m_scaleY": 1,
						"m_rotationAngle": 0,
						"m_isArtFlipped": false,
						"m_rotationRate": 0
					},
					{
						"m_eventType": "island",
						"m_imageID": 101,
						"m_parallaxLayer": 0,
						"m_drawLayer": 0,
						"m_position": {
							"x": 11849.5,
							"y": 280
						},
						"m_scaleX": 1,
						"m_scaleY": 1,
						"m_rotationAngle": 325,
						"m_isArtFlipped": false,
						"m_rotationRate": 0
					},
					{
						"m_eventType": "island",
						"m_imageID": 12,
						"m_parallaxLayer": -3,
						"m_drawLayer": 0,
						"m_position": {
							"x": 11855.750979999999,
							"y": 356
						},
						"m_scaleX": 0.6000000000000001,
						"m_scaleY": 0.6000000000000001,
						"m_rotationAngle": 0,
						"m_isArtFlipped": false,
						"m_rotationRate": -7
					},
					{
						"m_eventType": "island",
						"m_imageID": 101,
						"m_parallaxLayer": 0,
						"m_drawLayer": 0,
						"m_position": {
							"x": 11882.3125,
							"y": 276
						},
						"m_scaleX": 1,
						"m_scaleY": 1,
						"m_rotationAngle": 5,
						"m_isArtFlipped": false,
						"m_rotationRate": 0
					},
					{
						"m_eventType": "island",
						"m_imageID": 7,
						"m_parallaxLayer": 0,
						"m_drawLayer": 2,
						"m_position": {
							"x": 11908.874999999998,
							"y": 221
						},
						"m_scaleX": 1,
						"m_scaleY": 1,
						"m_rotationAngle": 0,
						"m_isArtFlipped": false,
						"m_rotationRate": 0
					},
					{
						"m_eventType": "island",
						"m_imageID": 12,
						"m_parallaxLayer": 4,
						"m_drawLayer": 0,
						"m_position": {
							"x": 11913.22363,
							"y": 139
						},
						"m_scaleX": 0.8,
						"m_scaleY": 0.8,
						"m_rotationAngle": 0,
						"m_isArtFlipped": false,
						"m_rotationRate": 2
					},
					{
						"m_eventType": "island",
						"m_imageID": 101,
						"m_parallaxLayer": 0,
						"m_drawLayer": 0,
						"m_position": {
							"x": 11940.906299999999,
							"y": 302
						},
						"m_scaleX": 1,
						"m_scaleY": 1,
						"m_rotationAngle": 0,
						"m_isArtFlipped": false,
						"m_rotationRate": 0
					},
					{
						"m_eventType": "island",
						"m_imageID": 4,
						"m_parallaxLayer": 0,
						"m_drawLayer": 0,
						"m_position": {
							"x": 11979.968799999999,
							"y": 228
						},
						"m_scaleX": 1,
						"m_scaleY": 1,
						"m_rotationAngle": 0,
						"m_isArtFlipped": true,
						"m_rotationRate": 0
					},
					{
						"m_eventType": "island",
						"m_imageID": 100,
						"m_parallaxLayer": 2,
						"m_drawLayer": 0,
						"m_position": {
							"x": 12047.25976599999,
							"y": 239
						},
						"m_scaleX": 0.8,
						"m_scaleY": 0.8,
						"m_rotationAngle": 0,
						"m_isArtFlipped": true,
						"m_rotationRate": 0
					},
					{
						"m_eventType": "island",
						"m_imageID": 101,
						"m_parallaxLayer": 0,
						"m_drawLayer": 0,
						"m_position": {
							"x": 12058.874999999998,
							"y": 367
						},
						"m_scaleX": 1,
						"m_scaleY": 1,
						"m_rotationAngle": 0,
						"m_isArtFlipped": false,
						"m_rotationRate": 0
					},
					{
						"m_eventType": "island",
						"m_imageID": 4,
						"m_parallaxLayer": 0,
						"m_drawLayer": 0,
						"m_position": {
							"x": 12097.9375,
							"y": 295
						},
						"m_scaleX": 1,
						"m_scaleY": 1,
						"m_rotationAngle": 0,
						"m_isArtFlipped": true,
						"m_rotationRate": 0
					},
					{
						"m_eventType": "island",
						"m_imageID": 6,
						"m_parallaxLayer": 0,
						"m_drawLayer": 2,
						"m_position": {
							"x": 12158.0938,
							"y": 348
						},
						"m_scaleX": 1,
						"m_scaleY": 1,
						"m_rotationAngle": 0,
						"m_isArtFlipped": true,
						"m_rotationRate": 0
					},
					{
						"m_eventType": "island",
						"m_imageID": 101,
						"m_parallaxLayer": 0,
						"m_drawLayer": 0,
						"m_position": {
							"x": 12194.0313,
							"y": 463
						},
						"m_scaleX": 1,
						"m_scaleY": 1,
						"m_rotationAngle": 350,
						"m_isArtFlipped": false,
						"m_rotationRate": 0
					},
					{
						"m_eventType": "island",
						"m_imageID": 102,
						"m_parallaxLayer": 0,
						"m_drawLayer": -3,
						"m_position": {
							"x": 12222.9375,
							"y": 492
						},
						"m_scaleX": 1,
						"m_scaleY": 1,
						"m_rotationAngle": 0,
						"m_isArtFlipped": false,
						"m_rotationRate": 0
					},
					{
						"m_eventType": "island",
						"m_imageID": 101,
						"m_parallaxLayer": 0,
						"m_drawLayer": 0,
						"m_position": {
							"x": 12229.968799999999,
							"y": 469
						},
						"m_scaleX": 1,
						"m_scaleY": 1,
						"m_rotationAngle": 325,
						"m_isArtFlipped": false,
						"m_rotationRate": 0
					},
					{
						"m_eventType": "island",
						"m_imageID": 5,
						"m_parallaxLayer": 0,
						"m_drawLayer": 0,
						"m_position": {
							"x": 12229.968799999999,
							"y": 354
						},
						"m_scaleX": 1,
						"m_scaleY": 1,
						"m_rotationAngle": 0,
						"m_isArtFlipped": false,
						"m_rotationRate": 0
					},
					{
						"m_eventType": "island",
						"m_imageID": 101,
						"m_parallaxLayer": 0,
						"m_drawLayer": 0,
						"m_position": {
							"x": 12264.3438,
							"y": 464
						},
						"m_scaleX": 1,
						"m_scaleY": 1,
						"m_rotationAngle": 5,
						"m_isArtFlipped": false,
						"m_rotationRate": 0
					},
					{
						"m_eventType": "island",
						"m_imageID": 11,
						"m_parallaxLayer": 1,
						"m_drawLayer": -1,
						"m_position": {
							"x": 12268.69238299999,
							"y": 141
						},
						"m_scaleX": 0.4,
						"m_scaleY": 0.4,
						"m_rotationAngle": 0,
						"m_isArtFlipped": false,
						"m_rotationRate": 13
					},
					{
						"m_eventType": "island",
						"m_imageID": 6,
						"m_parallaxLayer": 0,
						"m_drawLayer": 2,
						"m_position": {
							"x": 12293.25,
							"y": 352
						},
						"m_scaleX": 1,
						"m_scaleY": 1,
						"m_rotationAngle": 0,
						"m_isArtFlipped": false,
						"m_rotationRate": 0
					},
					{
						"m_eventType": "island",
						"m_imageID": 4,
						"m_parallaxLayer": 0,
						"m_drawLayer": 0,
						"m_position": {
							"x": 12357.3125,
							"y": 297
						},
						"m_scaleX": 1,
						"m_scaleY": 1,
						"m_rotationAngle": 0,
						"m_isArtFlipped": false,
						"m_rotationRate": 0
					},
					{
						"m_eventType": "island",
						"m_imageID": 101,
						"m_parallaxLayer": 0,
						"m_drawLayer": 0,
						"m_position": {
							"x": 12396.374999999998,
							"y": 372
						},
						"m_scaleX": 1,
						"m_scaleY": 1,
						"m_rotationAngle": 0,
						"m_isArtFlipped": false,
						"m_rotationRate": 0
					},
					{
						"m_eventType": "island",
						"m_imageID": 7,
						"m_parallaxLayer": 0,
						"m_drawLayer": 2,
						"m_position": {
							"x": 12425.906299999999,
							"y": 291
						},
						"m_scaleX": 1,
						"m_scaleY": 1,
						"m_rotationAngle": 0,
						"m_isArtFlipped": true,
						"m_rotationRate": 0
					},
					{
						"m_eventType": "island",
						"m_imageID": 101,
						"m_parallaxLayer": 0,
						"m_drawLayer": 0,
						"m_position": {
							"x": 12454.0313,
							"y": 344
						},
						"m_scaleX": 1,
						"m_scaleY": 1,
						"m_rotationAngle": 350,
						"m_isArtFlipped": false,
						"m_rotationRate": 0
					},
					{
						"m_eventType": "island",
						"m_imageID": 102,
						"m_parallaxLayer": 0,
						"m_drawLayer": -3,
						"m_position": {
							"x": 12482.156299999999,
							"y": 376
						},
						"m_scaleX": 1,
						"m_scaleY": 1,
						"m_rotationAngle": 0,
						"m_isArtFlipped": false,
						"m_rotationRate": 0
					},
					{
						"m_eventType": "island",
						"m_imageID": 5,
						"m_parallaxLayer": 0,
						"m_drawLayer": 0,
						"m_position": {
							"x": 12489.1875,
							"y": 237
						},
						"m_scaleX": 1,
						"m_scaleY": 1,
						"m_rotationAngle": 0,
						"m_isArtFlipped": false,
						"m_rotationRate": 0
					},
					{
						"m_eventType": "island",
						"m_imageID": 101,
						"m_parallaxLayer": 0,
						"m_drawLayer": 0,
						"m_position": {
							"x": 12490.75,
							"y": 352
						},
						"m_scaleX": 1,
						"m_scaleY": 1,
						"m_rotationAngle": 325,
						"m_isArtFlipped": false,
						"m_rotationRate": 0
					},
					{
						"m_eventType": "island",
						"m_imageID": 101,
						"m_parallaxLayer": 0,
						"m_drawLayer": 0,
						"m_position": {
							"x": 12524.3438,
							"y": 348
						},
						"m_scaleX": 1,
						"m_scaleY": 1,
						"m_rotationAngle": 5,
						"m_isArtFlipped": false,
						"m_rotationRate": 0
					},
					{
						"m_eventType": "island",
						"m_imageID": 4,
						"m_parallaxLayer": 0,
						"m_drawLayer": 0,
						"m_position": {
							"x": 7137.610000000001,
							"y": 288
						},
						"m_scaleX": 1,
						"m_scaleY": 1,
						"m_rotationAngle": 0,
						"m_isArtFlipped": true,
						"m_rotationRate": 0
					},
					{
						"m_position": {
							"x": 6353.125000000001,
							"y": 490.0
						},
						"m_imageID": 102,
						"m_eventType": "island",
						"m_name": "",
						"m_toggleName": "",
						"m_dataString": "",
						"m_unlockedFrom": "",
						"m_visibleFrom": "",
						"m_parentEvent": "",
						"m_displayText": "",
						"m_cost": 0,
						"m_autoVisible": false,
						"m_completedNarrationID": "",
						"m_unlockedNarrationID": "",
						"m_worldMapTutorial": "none",
						"m_worldMapTutorialVisibleWhen": "unlocked",
						"m_isArtFlipped": false,
						"m_levelNodeType": "normal",
						"m_isChallengeType": false,
						"m_drawLayer": 0,
						"m_rotationAngle": 0,
						"m_rotationRate": 0.0,
						"m_scaleX": 1.1800000000000002,
						"m_scaleY": 1.1800000000000002,
						"m_parallaxLayer": 0,
						"m_eventId": 69,
						"m_filter": 0,
						"m_inheritAssetFilter": true
					}
				],
				"m_eventList": [
					{
						"m_position": {
							"x": 7698,
							"y": -37
						},
						"m_eventId": 0,
						"m_eventType": "star_gate",
						"m_name": "future_stargate_start",
						"m_parentEvent": "",
						"m_unlockedFrom": "egypt_level_1",
						"m_visibleFrom": "",
						"m_autoVisible": true,
						"m_isChallengeType": false,
						"m_cost": 10
					},
					{
						"m_position": {
							"x": 5736.200194999999,
							"y": 263.200073
						},
						"m_eventId": 1,
						"m_eventType": "level",
						"m_name": "future_level_1",
						"m_parentEvent": "",
						"m_unlockedFrom": "future_stargate_start",
						"m_visibleFrom": "",
						"m_autoVisible": true,
						"m_isChallengeType": false,
						"m_dataString": "future1",
						"m_levelNodeType": "normal",
						"m_displayText": "1",
						"m_unlockedNarrationID": "",
						"m_completedNarrationID": "",
						"m_worldMapTutorial": "none",
						"m_worldMapTutorialVisibleWhen": "unlocked",
						"m_toggleName": ""
					},
					{
						"m_position": {
							"x": 5850,
							"y": 328
						},
						"m_eventId": 2,
						"m_eventType": "level",
						"m_name": "future_level_2",
						"m_parentEvent": "future_level_1",
						"m_unlockedFrom": "",
						"m_visibleFrom": "",
						"m_autoVisible": true,
						"m_isChallengeType": false,
						"m_dataString": "future2",
						"m_levelNodeType": "normal",
						"m_displayText": "2",
						"m_unlockedNarrationID": "",
						"m_completedNarrationID": "",
						"m_worldMapTutorial": "none",
						"m_worldMapTutorialVisibleWhen": "unlocked",
						"m_toggleName": ""
					},
					{
						"m_position": {
							"x": 5979,
							"y": 397
						},
						"m_eventId": 3,
						"m_eventType": "level",
						"m_name": "future_level_3",
						"m_parentEvent": "future_level_2",
						"m_unlockedFrom": "",
						"m_visibleFrom": "",
						"m_autoVisible": true,
						"m_isChallengeType": false,
						"m_dataString": "future3",
						"m_levelNodeType": "normal",
						"m_displayText": "3",
						"m_unlockedNarrationID": "",
						"m_completedNarrationID": "",
						"m_worldMapTutorial": "none",
						"m_worldMapTutorialVisibleWhen": "unlocked",
						"m_toggleName": ""
					},
					{
						"m_position": {
							"x": 6112,
							"y": 339
						},
						"m_eventId": 4,
						"m_eventType": "level",
						"m_name": "future_level_4",
						"m_parentEvent": "future_level_3",
						"m_unlockedFrom": "",
						"m_visibleFrom": "",
						"m_autoVisible": true,
						"m_isChallengeType": false,
						"m_dataString": "future4",
						"m_levelNodeType": "normal",
						"m_displayText": "4",
						"m_unlockedNarrationID": "",
						"m_completedNarrationID": "",
						"m_worldMapTutorial": "none",
						"m_worldMapTutorialVisibleWhen": "unlocked",
						"m_toggleName": ""
					},
					{
						"m_position": {
							"x": 6234,
							"y": 269
						},
						"m_eventId": 5,
						"m_eventType": "level",
						"m_name": "future_level_5",
						"m_parentEvent": "future_level_4",
						"m_unlockedFrom": "",
						"m_visibleFrom": "",
						"m_autoVisible": true,
						"m_isChallengeType": false,
						"m_dataString": "future5",
						"m_levelNodeType": "normal",
						"m_displayText": "5",
						"m_unlockedNarrationID": "",
						"m_completedNarrationID": "",
						"m_worldMapTutorial": "none",
						"m_worldMapTutorialVisibleWhen": "unlocked",
						"m_toggleName": ""
					},
					{
						"m_position": {
							"x": 6357,
							"y": 205
						},
						"m_eventId": 6,
						"m_eventType": "level",
						"m_name": "future_level_6",
						"m_parentEvent": "future_level_5",
						"m_unlockedFrom": "",
						"m_visibleFrom": "",
						"m_autoVisible": true,
						"m_isChallengeType": false,
						"m_dataString": "future6",
						"m_levelNodeType": "normal",
						"m_displayText": "6",
						"m_unlockedNarrationID": "",
						"m_completedNarrationID": "",
						"m_worldMapTutorial": "none",
						"m_worldMapTutorialVisibleWhen": "unlocked",
						"m_toggleName": ""
					},
					{
						"m_position": {
							"x": 6489,
							"y": 273
						},
						"m_eventId": 7,
						"m_eventType": "level",
						"m_name": "future_level_7",
						"m_parentEvent": "future_level_6",
						"m_unlockedFrom": "",
						"m_visibleFrom": "",
						"m_autoVisible": true,
						"m_isChallengeType": false,
						"m_dataString": "future7",
						"m_levelNodeType": "normal",
						"m_displayText": "7",
						"m_unlockedNarrationID": "",
						"m_completedNarrationID": "",
						"m_worldMapTutorial": "none",
						"m_worldMapTutorialVisibleWhen": "unlocked",
						"m_toggleName": ""
					},
					{
						"m_position": {
							"x": 6610,
							"y": 334
						},
						"m_eventId": 8,
						"m_eventType": "level",
						"m_name": "future_level_8",
						"m_parentEvent": "future_level_7",
						"m_unlockedFrom": "",
						"m_visibleFrom": "",
						"m_autoVisible": true,
						"m_isChallengeType": false,
						"m_dataString": "future8",
						"m_levelNodeType": "normal",
						"m_displayText": "8",
						"m_unlockedNarrationID": "",
						"m_completedNarrationID": "",
						"m_worldMapTutorial": "none",
						"m_worldMapTutorialVisibleWhen": "unlocked",
						"m_toggleName": ""
					},
					{
						"m_position": {
							"x": 6739,
							"y": 402
						},
						"m_eventId": 9,
						"m_eventType": "level",
						"m_name": "future_level_9",
						"m_parentEvent": "future_level_8",
						"m_unlockedFrom": "",
						"m_visibleFrom": "",
						"m_autoVisible": true,
						"m_isChallengeType": false,
						"m_dataString": "future9",
						"m_levelNodeType": "normal",
						"m_displayText": "9",
						"m_unlockedNarrationID": "",
						"m_completedNarrationID": "",
						"m_worldMapTutorial": "none",
						"m_worldMapTutorialVisibleWhen": "unlocked",
						"m_toggleName": ""
					},
					{
						"m_position": {
							"x": 6867,
							"y": 342
						},
						"m_eventId": 10,
						"m_eventType": "level",
						"m_name": "future_level_10",
						"m_parentEvent": "future_level_9",
						"m_unlockedFrom": "",
						"m_visibleFrom": "",
						"m_autoVisible": true,
						"m_isChallengeType": false,
						"m_dataString": "future10",
						"m_levelNodeType": "normal",
						"m_displayText": "10",
						"m_unlockedNarrationID": "",
						"m_completedNarrationID": "",
						"m_worldMapTutorial": "none",
						"m_worldMapTutorialVisibleWhen": "unlocked",
						"m_toggleName": ""
					},
					{
						"m_position": {
							"x": 6994,
							"y": 279
						},
						"m_eventId": 5,
						"m_eventType": "level",
						"m_name": "survival_endless_future",
						"m_parentEvent": "",
						"m_unlockedFrom": "",
						"m_visibleFrom": "",
						"m_autoVisible": true,
						"m_isChallengeType": true,
						"m_dataString": "survival/survival_future",
						"m_levelNodeType": "minigame",
						"m_displayText": "Survival",
						"m_unlockedNarrationID": "",
						"m_completedNarrationID": "",
						"m_worldMapTutorial": "none",
						"m_worldMapTutorialVisibleWhen": "unlocked",
						"m_toggleName": ""
					},
					{
						"m_position": {
							"x": 7277.610000000001,
							"y": 399
						},
						"m_eventId": 10,
						"m_eventType": "level",
						"m_name": "survival_endless_future2",
						"m_parentEvent": "",
						"m_unlockedFrom": "",
						"m_visibleFrom": "",
						"m_autoVisible": true,
						"m_isChallengeType": true,
						"m_dataString": "survival/survival_future2",
						"m_levelNodeType": "minigame",
						"m_displayText": "Survival II",
						"m_unlockedNarrationID": "",
						"m_completedNarrationID": "",
						"m_worldMapTutorial": "none",
						"m_worldMapTutorialVisibleWhen": "unlocked",
						"m_toggleName": ""
					},
					{
						"m_position": {
							"x": 6359.0,
							"y": 385.0
						},
						"m_eventId": 50,
						"m_eventType": "level",
						"m_name": "future_level_dangerroom",
						"m_parentEvent": "",
						"m_unlockedFrom": "future_level_1",
						"m_visibleFrom": "",
						"m_autoVisible": false,
						"m_isChallengeType": false,
						"m_dataString": "future_dangerroom",
						"m_levelNodeType": "normal",
						"m_displayText": "10004",
						"m_unlockedNarrationID": "",
						"m_completedNarrationID": "",
						"m_worldMapTutorial": "none",
						"m_worldMapTutorialVisibleWhen": "unlocked",
						"m_toggleName": ""
					}
				]
			}
		}
	]
}