{
	"#comment": "Empty Heart",
	"#comment": "cowboy/cowboy 7",
	"objects": [
		{
			"objclass": "LevelDefinition",
			"objdata": {
				"RandomLevelSet": [
					"cowboy/cowboy0701",
					"cowboy/cowboy0702",
					"cowboy/cowboy0703",
					"cowboy/cowboy0704",
					"cowboy/cowboy0705",
					"cowboy/cowboy0706",
					"cowboy/cowboy0707",
					"cowboy/cowboy0708",
					"cowboy/cowboy0709",
					"cowboy/cowboy0710",
					"cowboy/cowboy0711",
					"cowboy/cowboy0712",
					"cowboy/cowboy0713",
					"cowboy/cowboy0714",
					"cowboy/cowboy0715",
					"cowboy/cowboy0716",
					"cowboy/cowboy0717",
					"cowboy/cowboy0718",
					"cowboy/cowboy0719",
					"cowboy/cowboy0720",
					"cowboy/cowboy0721",
					"cowboy/cowboy0722",
					"cowboy/cowboy0723",
					"cowboy/cowboy0724",
					"cowboy/cowboy0725",
					"cowboy/cowboy0726",
					"cowboy/cowboy0727",
					"cowboy/cowboy0728",
					"cowboy/cowboy0729",
					"cowboy/cowboy0730",
					"cowboy/cowboy0731",
					"cowboy/cowboy0732",
					"cowboy/cowboy0733",
					"cowboy/cowboy0734",
					"cowboy/cowboy0735",
					"cowboy/cowboy0736",
					"cowboy/cowboy0737",
					"cowboy/cowboy0738",
					"cowboy/cowboy0739",
					"cowboy/cowboy0740",
					"cowboy/cowboy0741",
					"cowboy/cowboy0742",
					"cowboy/cowboy0743",
					"cowboy/cowboy0744",
					"cowboy/cowboy0745",
					"cowboy/cowboy0746",
					"cowboy/cowboy0747",
					"cowboy/cowboy0748",
					"cowboy/cowboy0749",
					"cowboy/cowboy0750",
					"cowboy/cowboy0750",
					"cowboy/cowboy0751",
					"cowboy/cowboy0752",
					"cowboy/cowboy0753",
					"cowboy/cowboy0754",
					"cowboy/cowboy0755",
					"cowboy/cowboy0756",
					"cowboy/cowboy0757",
					"cowboy/cowboy0758",
					"cowboy/cowboy0759"
				]
			}
		}
	],
	"version": 1
}