{
	"###": "This Map Create By SPC-Util : Map-Designer",
	"version": 1,
	"objects": [
		{
			"objclass": "WorldData",
			"objdata": {
				"m_worldName": "egypt",
				"m_boundingRect": {
					"mX": -819,
					"mY": -103,
					"mWidth": 2750,
					"mHeight": 978
				},
				"m_worldId": 2,
				"m_resGroupID": 7,
				"m_version": 1,
				"m_creationTime": 227852867,
				"m_mapPieces": [
					{
						"m_eventType": "island",
						"m_imageID": 0,
						"m_parallaxLayer": 0,
						"m_drawLayer": 0,
						"m_position": {
							"x": -624.0624999999999,
							"y": 111
						},
						"m_scaleX": 1,
						"m_scaleY": 1,
						"m_rotationAngle": 0,
						"m_isArtFlipped": false,
						"m_rotationRate": 0
					},
					{
						"m_eventType": "island",
						"m_imageID": 10,
						"m_parallaxLayer": 0,
						"m_drawLayer": -1,
						"m_position": {
							"x": 1163.1875,
							"y": 459
						},
						"m_scaleX": 1,
						"m_scaleY": 1,
						"m_rotationAngle": 0,
						"m_isArtFlipped": false,
						"m_rotationRate": 0
					},
					{
						"m_eventType": "island",
						"m_imageID": 4,
						"m_parallaxLayer": 0,
						"m_drawLayer": 0,
						"m_position": {
							"x": -419.6875,
							"y": 394
						},
						"m_scaleX": 1,
						"m_scaleY": 1,
						"m_rotationAngle": 0,
						"m_isArtFlipped": false,
						"m_rotationRate": 0
					},
					{
						"m_eventType": "island",
						"m_imageID": 4,
						"m_parallaxLayer": 0,
						"m_drawLayer": -1,
						"m_position": {
							"x": -279.0625,
							"y": 459
						},
						"m_scaleX": 0.8,
						"m_scaleY": 0.8,
						"m_rotationAngle": 0,
						"m_isArtFlipped": false,
						"m_rotationRate": 0
					},
					{
						"m_eventType": "island",
						"m_imageID": 4,
						"m_parallaxLayer": 0,
						"m_drawLayer": 0,
						"m_position": {
							"x": -1.7187500000000002,
							"y": 440
						},
						"m_scaleX": 0.7000000000000001,
						"m_scaleY": 0.7000000000000001,
						"m_rotationAngle": 0,
						"m_isArtFlipped": false,
						"m_rotationRate": 0
					},
					{
						"m_eventType": "island",
						"m_imageID": 8,
						"m_parallaxLayer": 0,
						"m_drawLayer": 0,
						"m_position": {
							"x": 130.28125,
							"y": 361
						},
						"m_scaleX": 1,
						"m_scaleY": 1,
						"m_rotationAngle": 0,
						"m_isArtFlipped": false,
						"m_rotationRate": 0
					},
					{
						"m_eventType": "island",
						"m_imageID": 8,
						"m_parallaxLayer": 0,
						"m_drawLayer": 0,
						"m_position": {
							"x": 283.09374999999994,
							"y": 277
						},
						"m_scaleX": 1,
						"m_scaleY": 1,
						"m_rotationAngle": 0,
						"m_isArtFlipped": false,
						"m_rotationRate": 0
					},
					{
						"m_eventType": "island",
						"m_imageID": 4,
						"m_parallaxLayer": 0,
						"m_drawLayer": -1,
						"m_position": {
							"x": 462.90624999999994,
							"y": 220
						},
						"m_scaleX": 1,
						"m_scaleY": 1,
						"m_rotationAngle": 0,
						"m_isArtFlipped": false,
						"m_rotationRate": 0
					},
					{
						"m_eventType": "island",
						"m_imageID": 8,
						"m_parallaxLayer": 0,
						"m_drawLayer": 0,
						"m_position": {
							"x": 1180.78125,
							"y": 422
						},
						"m_scaleX": 1,
						"m_scaleY": 1,
						"m_rotationAngle": 0,
						"m_isArtFlipped": false,
						"m_rotationRate": 0
					},
					{
						"m_eventType": "island",
						"m_imageID": 4,
						"m_parallaxLayer": 0,
						"m_drawLayer": 0,
						"m_position": {
							"x": 801.1562499999999,
							"y": 327
						},
						"m_scaleX": 1,
						"m_scaleY": 1,
						"m_rotationAngle": 0,
						"m_isArtFlipped": false,
						"m_rotationRate": 0
					},
					{
						"m_eventType": "island",
						"m_imageID": 4,
						"m_parallaxLayer": 0,
						"m_drawLayer": 0,
						"m_position": {
							"x": 964.46875,
							"y": 426
						},
						"m_scaleX": 1,
						"m_scaleY": 1,
						"m_rotationAngle": 0,
						"m_isArtFlipped": false,
						"m_rotationRate": 0
					},
					{
						"m_eventType": "island",
						"m_imageID": 4,
						"m_parallaxLayer": 0,
						"m_drawLayer": 0,
						"m_position": {
							"x": 1334.03125,
							"y": 295
						},
						"m_scaleX": 1,
						"m_scaleY": 1,
						"m_rotationAngle": 0,
						"m_isArtFlipped": false,
						"m_rotationRate": 0
					},
					{
						"m_eventType": "island",
						"m_imageID": 4,
						"m_parallaxLayer": 0,
						"m_drawLayer": 0,
						"m_position": {
							"x": 1694.25,
							"y": 311
						},
						"m_scaleX": 1,
						"m_scaleY": 1,
						"m_rotationAngle": 0,
						"m_isArtFlipped": false,
						"m_rotationRate": 0
					},
					{
						"m_eventType": "island",
						"m_imageID": 3,
						"m_parallaxLayer": 0,
						"m_drawLayer": 0,
						"m_position": {
							"x": 1818.875,
							"y": 397
						},
						"m_scaleX": 1,
						"m_scaleY": 1,
						"m_rotationAngle": 0,
						"m_isArtFlipped": false,
						"m_rotationRate": 0
					},
					{
						"m_eventType": "island",
						"m_imageID": 8,
						"m_parallaxLayer": 0,
						"m_drawLayer": 0,
						"m_position": {
							"x": 374.90624999999994,
							"y": 401
						},
						"m_scaleX": 1,
						"m_scaleY": 1,
						"m_rotationAngle": 0,
						"m_isArtFlipped": false,
						"m_rotationRate": 0
					},
					{
						"m_eventType": "island",
						"m_imageID": 21,
						"m_parallaxLayer": 9,
						"m_drawLayer": 0,
						"m_position": {
							"x": 169.041183,
							"y": 120
						},
						"m_scaleX": 0.7000000000000001,
						"m_scaleY": 0.7000000000000001,
						"m_rotationAngle": 0,
						"m_isArtFlipped": false,
						"m_rotationRate": 0
					},
					{
						"m_eventType": "island",
						"m_imageID": 6,
						"m_parallaxLayer": 0,
						"m_drawLayer": 2,
						"m_position": {
							"x": 1298.25,
							"y": 329
						},
						"m_scaleX": 1,
						"m_scaleY": 1,
						"m_rotationAngle": 0,
						"m_isArtFlipped": false,
						"m_rotationRate": 0
					},
					{
						"m_eventType": "island",
						"m_imageID": 104,
						"m_parallaxLayer": 0,
						"m_drawLayer": 0,
						"m_position": {
							"x": -371.25,
							"y": 456
						},
						"m_scaleX": 0.6000000000000001,
						"m_scaleY": 0.6000000000000001,
						"m_rotationAngle": 0,
						"m_isArtFlipped": false,
						"m_rotationRate": 0
					},
					{
						"m_eventType": "island",
						"m_imageID": 104,
						"m_parallaxLayer": 0,
						"m_drawLayer": 0,
						"m_position": {
							"x": -334.53124999999994,
							"y": 524
						},
						"m_scaleX": 1,
						"m_scaleY": 1,
						"m_rotationAngle": 0,
						"m_isArtFlipped": true,
						"m_rotationRate": 0
					},
					{
						"m_eventType": "island",
						"m_imageID": 4,
						"m_parallaxLayer": 0,
						"m_drawLayer": -1,
						"m_position": {
							"x": 282.3125,
							"y": 293
						},
						"m_scaleX": 1,
						"m_scaleY": 1,
						"m_rotationAngle": 0,
						"m_isArtFlipped": false,
						"m_rotationRate": 0
					},
					{
						"m_eventType": "island",
						"m_imageID": 11,
						"m_parallaxLayer": 0,
						"m_drawLayer": -1,
						"m_position": {
							"x": 317.46874999999994,
							"y": 321
						},
						"m_scaleX": 1,
						"m_scaleY": 1,
						"m_rotationAngle": 0,
						"m_isArtFlipped": false,
						"m_rotationRate": 0
					},
					{
						"m_eventType": "island",
						"m_imageID": 3,
						"m_parallaxLayer": 0,
						"m_drawLayer": 0,
						"m_position": {
							"x": -115.78125000000001,
							"y": 453
						},
						"m_scaleX": 1,
						"m_scaleY": 1,
						"m_rotationAngle": 0,
						"m_isArtFlipped": false,
						"m_rotationRate": 0
					},
					{
						"m_eventType": "island",
						"m_imageID": 104,
						"m_parallaxLayer": 0,
						"m_drawLayer": 0,
						"m_position": {
							"x": 48.28125,
							"y": 498
						},
						"m_scaleX": 1,
						"m_scaleY": 1,
						"m_rotationAngle": 0,
						"m_isArtFlipped": false,
						"m_rotationRate": 0
					},
					{
						"m_eventType": "island",
						"m_imageID": 5,
						"m_parallaxLayer": 0,
						"m_drawLayer": 0,
						"m_position": {
							"x": -143.125,
							"y": 502
						},
						"m_scaleX": 1,
						"m_scaleY": 1,
						"m_rotationAngle": 0,
						"m_isArtFlipped": true,
						"m_rotationRate": 0
					},
					{
						"m_eventType": "island",
						"m_imageID": 104,
						"m_parallaxLayer": 0,
						"m_drawLayer": 1,
						"m_position": {
							"x": 879.5937500000001,
							"y": 378
						},
						"m_scaleX": 1,
						"m_scaleY": 1,
						"m_rotationAngle": 0,
						"m_isArtFlipped": false,
						"m_rotationRate": 0
					},
					{
						"m_eventType": "island",
						"m_imageID": 11,
						"m_parallaxLayer": 0,
						"m_drawLayer": -1,
						"m_position": {
							"x": 797.25,
							"y": 314
						},
						"m_scaleX": 1,
						"m_scaleY": 1,
						"m_rotationAngle": 0,
						"m_isArtFlipped": false,
						"m_rotationRate": 0
					},
					{
						"m_eventType": "island",
						"m_imageID": 8,
						"m_parallaxLayer": 0,
						"m_drawLayer": 0,
						"m_position": {
							"x": 462.125,
							"y": 219
						},
						"m_scaleX": 0.7000000000000001,
						"m_scaleY": 0.7000000000000001,
						"m_rotationAngle": 0,
						"m_isArtFlipped": false,
						"m_rotationRate": 0
					},
					{
						"m_eventType": "island",
						"m_imageID": 106,
						"m_parallaxLayer": 0,
						"m_drawLayer": 0,
						"m_position": {
							"x": -425.15625,
							"y": 472
						},
						"m_scaleX": 1,
						"m_scaleY": 1,
						"m_rotationAngle": 0,
						"m_isArtFlipped": false,
						"m_rotationRate": 0
					},
					{
						"m_eventType": "island",
						"m_imageID": 4,
						"m_parallaxLayer": 0,
						"m_drawLayer": -1,
						"m_position": {
							"x": 136.53125,
							"y": 375
						},
						"m_scaleX": 1,
						"m_scaleY": 1,
						"m_rotationAngle": 0,
						"m_isArtFlipped": false,
						"m_rotationRate": 0
					},
					{
						"m_eventType": "island",
						"m_imageID": 105,
						"m_parallaxLayer": 0,
						"m_drawLayer": 1,
						"m_position": {
							"x": 1523.0625,
							"y": 353
						},
						"m_scaleX": 1,
						"m_scaleY": 1,
						"m_rotationAngle": 0,
						"m_isArtFlipped": true,
						"m_rotationRate": 0
					},
					{
						"m_eventType": "island",
						"m_imageID": 21,
						"m_parallaxLayer": 9,
						"m_drawLayer": -2,
						"m_position": {
							"x": -131.958862,
							"y": 118
						},
						"m_scaleX": 0.7000000000000001,
						"m_scaleY": 0.7000000000000001,
						"m_rotationAngle": 0,
						"m_isArtFlipped": false,
						"m_rotationRate": 0
					},
					{
						"m_eventType": "island",
						"m_imageID": 13,
						"m_parallaxLayer": 10,
						"m_drawLayer": 0,
						"m_position": {
							"x": -407,
							"y": 47
						},
						"m_scaleX": 0.9,
						"m_scaleY": 0.9,
						"m_rotationAngle": 0,
						"m_isArtFlipped": false,
						"m_rotationRate": 0
					},
					{
						"m_eventType": "island",
						"m_imageID": 104,
						"m_parallaxLayer": 0,
						"m_drawLayer": 1,
						"m_position": {
							"x": 1752.0625,
							"y": 380
						},
						"m_scaleX": 1,
						"m_scaleY": 1,
						"m_rotationAngle": 0,
						"m_isArtFlipped": false,
						"m_rotationRate": 0
					},
					{
						"m_eventType": "island",
						"m_imageID": 105,
						"m_parallaxLayer": 0,
						"m_drawLayer": 1,
						"m_position": {
							"x": 1684.09375,
							"y": 380
						},
						"m_scaleX": 1,
						"m_scaleY": 1,
						"m_rotationAngle": 0,
						"m_isArtFlipped": false,
						"m_rotationRate": 0
					},
					{
						"m_eventType": "island",
						"m_imageID": 4,
						"m_parallaxLayer": 0,
						"m_drawLayer": 0,
						"m_position": {
							"x": 1505.5625,
							"y": 277
						},
						"m_scaleX": 1,
						"m_scaleY": 1,
						"m_rotationAngle": 0,
						"m_isArtFlipped": false,
						"m_rotationRate": 0
					},
					{
						"m_eventType": "island",
						"m_imageID": 104,
						"m_parallaxLayer": 0,
						"m_drawLayer": 1,
						"m_position": {
							"x": 752.0937500000001,
							"y": 405
						},
						"m_scaleX": 1,
						"m_scaleY": 1,
						"m_rotationAngle": 0,
						"m_isArtFlipped": true,
						"m_rotationRate": 0
					},
					{
						"m_eventType": "island",
						"m_imageID": 104,
						"m_parallaxLayer": 0,
						"m_drawLayer": 0,
						"m_position": {
							"x": 1857.15625,
							"y": 471
						},
						"m_scaleX": 1,
						"m_scaleY": 1,
						"m_rotationAngle": 0,
						"m_isArtFlipped": false,
						"m_rotationRate": 0
					},
					{
						"m_eventType": "island",
						"m_imageID": 105,
						"m_parallaxLayer": 0,
						"m_drawLayer": 0,
						"m_position": {
							"x": 367.875,
							"y": 470
						},
						"m_scaleX": 1,
						"m_scaleY": 1,
						"m_rotationAngle": 0,
						"m_isArtFlipped": false,
						"m_rotationRate": 0
					},
					{
						"m_eventType": "island",
						"m_imageID": 22,
						"m_parallaxLayer": 9,
						"m_drawLayer": 0,
						"m_position": {
							"x": -491.740051,
							"y": 178
						},
						"m_scaleX": 0.7000000000000001,
						"m_scaleY": 0.7000000000000001,
						"m_rotationAngle": 0,
						"m_isArtFlipped": false,
						"m_rotationRate": 0
					},
					{
						"m_eventType": "island",
						"m_imageID": 24,
						"m_parallaxLayer": 6,
						"m_drawLayer": -1,
						"m_position": {
							"x": -69.59758000000001,
							"y": 211
						},
						"m_scaleX": 0.4,
						"m_scaleY": 0.4,
						"m_rotationAngle": 0,
						"m_isArtFlipped": false,
						"m_rotationRate": 0
					},
					{
						"m_eventType": "island",
						"m_imageID": 27,
						"m_parallaxLayer": 6,
						"m_drawLayer": 1,
						"m_position": {
							"x": -48.660088,
							"y": 206
						},
						"m_scaleX": 0.4,
						"m_scaleY": 0.4,
						"m_rotationAngle": 0,
						"m_isArtFlipped": false,
						"m_rotationRate": 0
					},
					{
						"m_eventType": "island",
						"m_imageID": 17,
						"m_parallaxLayer": 6,
						"m_drawLayer": 2,
						"m_position": {
							"x": -25.847578000000002,
							"y": 240
						},
						"m_scaleX": 0.4,
						"m_scaleY": 0.4,
						"m_rotationAngle": 0,
						"m_isArtFlipped": true,
						"m_rotationRate": 0
					},
					{
						"m_eventType": "island",
						"m_imageID": 17,
						"m_parallaxLayer": 6,
						"m_drawLayer": 2,
						"m_position": {
							"x": -51.472569,
							"y": 230
						},
						"m_scaleX": 0.6000000000000001,
						"m_scaleY": 0.6000000000000001,
						"m_rotationAngle": 0,
						"m_isArtFlipped": false,
						"m_rotationRate": 0
					},
					{
						"m_eventType": "island",
						"m_imageID": 18,
						"m_parallaxLayer": 6,
						"m_drawLayer": 2,
						"m_position": {
							"x": -79.597572,
							"y": 229
						},
						"m_scaleX": 0.4,
						"m_scaleY": 0.4,
						"m_rotationAngle": 0,
						"m_isArtFlipped": true,
						"m_rotationRate": 0
					},
					{
						"m_eventType": "island",
						"m_imageID": 23,
						"m_parallaxLayer": 7,
						"m_drawLayer": 0,
						"m_position": {
							"x": -289.4262999999999,
							"y": 179
						},
						"m_scaleX": 0.2,
						"m_scaleY": 0.2,
						"m_rotationAngle": 0,
						"m_isArtFlipped": false,
						"m_rotationRate": 0
					},
					{
						"m_eventType": "island",
						"m_imageID": 24,
						"m_parallaxLayer": 8,
						"m_drawLayer": 0,
						"m_position": {
							"x": -97.223854,
							"y": 150
						},
						"m_scaleX": 0.2,
						"m_scaleY": 0.2,
						"m_rotationAngle": 0,
						"m_isArtFlipped": false,
						"m_rotationRate": 0
					},
					{
						"m_eventType": "island",
						"m_imageID": 25,
						"m_parallaxLayer": 8,
						"m_drawLayer": 0,
						"m_position": {
							"x": 1.369858,
							"y": 161
						},
						"m_scaleX": 0.2,
						"m_scaleY": 0.2,
						"m_rotationAngle": 0,
						"m_isArtFlipped": false,
						"m_rotationRate": 0
					},
					{
						"m_eventType": "island",
						"m_imageID": 24,
						"m_parallaxLayer": 8,
						"m_drawLayer": -1,
						"m_position": {
							"x": -39.255142000000006,
							"y": 125
						},
						"m_scaleX": 0.2,
						"m_scaleY": 0.2,
						"m_rotationAngle": 0,
						"m_isArtFlipped": false,
						"m_rotationRate": 0
					},
					{
						"m_eventType": "island",
						"m_imageID": 26,
						"m_parallaxLayer": 8,
						"m_drawLayer": 1,
						"m_position": {
							"x": -28.317642,
							"y": 113
						},
						"m_scaleX": 0.30000000000000004,
						"m_scaleY": 0.30000000000000004,
						"m_rotationAngle": 355,
						"m_isArtFlipped": false,
						"m_rotationRate": 0
					},
					{
						"m_eventType": "island",
						"m_imageID": 16,
						"m_parallaxLayer": 8,
						"m_drawLayer": 4,
						"m_position": {
							"x": -71.56601,
							"y": 139
						},
						"m_scaleX": 0.2,
						"m_scaleY": 0.2,
						"m_rotationAngle": 0,
						"m_isArtFlipped": false,
						"m_rotationRate": 0
					},
					{
						"m_eventType": "island",
						"m_imageID": 16,
						"m_parallaxLayer": 8,
						"m_drawLayer": 2,
						"m_position": {
							"x": 12.02774,
							"y": 132
						},
						"m_scaleX": 0.2,
						"m_scaleY": 0.2,
						"m_rotationAngle": 345,
						"m_isArtFlipped": false,
						"m_rotationRate": 0
					},
					{
						"m_eventType": "island",
						"m_imageID": 16,
						"m_parallaxLayer": 8,
						"m_drawLayer": 2,
						"m_position": {
							"x": -125.47226,
							"y": 135
						},
						"m_scaleX": 0.2,
						"m_scaleY": 0.2,
						"m_rotationAngle": 0,
						"m_isArtFlipped": false,
						"m_rotationRate": 0
					},
					{
						"m_eventType": "island",
						"m_imageID": 16,
						"m_parallaxLayer": 8,
						"m_drawLayer": 2,
						"m_position": {
							"x": -87.97226,
							"y": 130
						},
						"m_scaleX": 0.2,
						"m_scaleY": 0.2,
						"m_rotationAngle": 0,
						"m_isArtFlipped": false,
						"m_rotationRate": 0
					},
					{
						"m_eventType": "island",
						"m_imageID": 16,
						"m_parallaxLayer": 8,
						"m_drawLayer": 2,
						"m_position": {
							"x": -62.97226,
							"y": 131
						},
						"m_scaleX": 0.1,
						"m_scaleY": 0.1,
						"m_rotationAngle": 0,
						"m_isArtFlipped": false,
						"m_rotationRate": 0
					},
					{
						"m_eventType": "island",
						"m_imageID": 16,
						"m_parallaxLayer": 8,
						"m_drawLayer": 2,
						"m_position": {
							"x": -1.25351,
							"y": 138
						},
						"m_scaleX": 0.2,
						"m_scaleY": 0.2,
						"m_rotationAngle": 0,
						"m_isArtFlipped": false,
						"m_rotationRate": 0
					},
					{
						"m_eventType": "island",
						"m_imageID": 16,
						"m_parallaxLayer": 8,
						"m_drawLayer": 2,
						"m_position": {
							"x": -21.56601,
							"y": 105
						},
						"m_scaleX": 0.2,
						"m_scaleY": 0.2,
						"m_rotationAngle": 0,
						"m_isArtFlipped": false,
						"m_rotationRate": 0
					},
					{
						"m_eventType": "island",
						"m_imageID": 20,
						"m_parallaxLayer": 8,
						"m_drawLayer": 3,
						"m_position": {
							"x": -41.09726,
							"y": 100
						},
						"m_scaleX": 0.4,
						"m_scaleY": 0.4,
						"m_rotationAngle": 0,
						"m_isArtFlipped": false,
						"m_rotationRate": 0
					},
					{
						"m_eventType": "island",
						"m_imageID": 107,
						"m_parallaxLayer": 3,
						"m_drawLayer": 0,
						"m_position": {
							"x": 2339.4199220000005,
							"y": 275
						},
						"m_scaleX": 1,
						"m_scaleY": 1,
						"m_rotationAngle": 0,
						"m_isArtFlipped": false,
						"m_rotationRate": 0
					},
					{
						"m_eventType": "island",
						"m_imageID": 103,
						"m_parallaxLayer": 4,
						"m_drawLayer": 3,
						"m_position": {
							"x": 1789.5913089999988,
							"y": 142
						},
						"m_scaleX": 1,
						"m_scaleY": 1,
						"m_rotationAngle": 0,
						"m_isArtFlipped": false,
						"m_rotationRate": 0
					},
					{
						"m_eventType": "island",
						"m_imageID": 101,
						"m_parallaxLayer": 10,
						"m_drawLayer": 3,
						"m_position": {
							"x": -636.568848,
							"y": 84
						},
						"m_scaleX": 1,
						"m_scaleY": 1,
						"m_rotationAngle": 0,
						"m_isArtFlipped": false,
						"m_rotationRate": 0
					},
					{
						"m_eventType": "island",
						"m_imageID": 101,
						"m_parallaxLayer": 10,
						"m_drawLayer": 3,
						"m_position": {
							"x": -293.600098,
							"y": 40
						},
						"m_scaleX": 1,
						"m_scaleY": 1,
						"m_rotationAngle": 0,
						"m_isArtFlipped": false,
						"m_rotationRate": 0
					},
					{
						"m_eventType": "island",
						"m_imageID": 101,
						"m_parallaxLayer": 10,
						"m_drawLayer": 3,
						"m_position": {
							"x": -81.88133199999999,
							"y": 61
						},
						"m_scaleX": 1,
						"m_scaleY": 1,
						"m_rotationAngle": 0,
						"m_isArtFlipped": false,
						"m_rotationRate": 0
					},
					{
						"m_eventType": "island",
						"m_imageID": 101,
						"m_parallaxLayer": 10,
						"m_drawLayer": 0,
						"m_position": {
							"x": -647.896973,
							"y": 217
						},
						"m_scaleX": 1,
						"m_scaleY": 1,
						"m_rotationAngle": 0,
						"m_isArtFlipped": false,
						"m_rotationRate": 0
					},
					{
						"m_eventType": "island",
						"m_imageID": 105,
						"m_parallaxLayer": 0,
						"m_drawLayer": 1,
						"m_position": {
							"x": 948.84375,
							"y": 492
						},
						"m_scaleX": 1,
						"m_scaleY": 1,
						"m_rotationAngle": 0,
						"m_isArtFlipped": false,
						"m_rotationRate": 0
					},
					{
						"m_eventType": "island",
						"m_imageID": 105,
						"m_parallaxLayer": 0,
						"m_drawLayer": -1,
						"m_position": {
							"x": 388.96874999999994,
							"y": 475
						},
						"m_scaleX": 1,
						"m_scaleY": 1,
						"m_rotationAngle": 0,
						"m_isArtFlipped": true,
						"m_rotationRate": 0
					},
					{
						"m_eventType": "island",
						"m_imageID": 6,
						"m_parallaxLayer": 0,
						"m_drawLayer": 1,
						"m_position": {
							"x": -92.34375,
							"y": 492
						},
						"m_scaleX": 1,
						"m_scaleY": 1,
						"m_rotationAngle": 0,
						"m_isArtFlipped": true,
						"m_rotationRate": 0
					},
					{
						"m_eventType": "island",
						"m_imageID": 100,
						"m_parallaxLayer": 0,
						"m_drawLayer": 0,
						"m_position": {
							"x": 6082.812500000001,
							"y": 310
						},
						"m_scaleX": 1,
						"m_scaleY": 1,
						"m_rotationAngle": 0,
						"m_isArtFlipped": false,
						"m_rotationRate": 0
					},
					{
						"m_eventType": "island",
						"m_imageID": 101,
						"m_parallaxLayer": 10,
						"m_drawLayer": 0,
						"m_position": {
							"x": -192.80743400000003,
							"y": 192
						},
						"m_scaleX": 1,
						"m_scaleY": 1,
						"m_rotationAngle": 0,
						"m_isArtFlipped": false,
						"m_rotationRate": 0
					},
					{
						"m_eventType": "island",
						"m_imageID": 103,
						"m_parallaxLayer": 8,
						"m_drawLayer": 2,
						"m_position": {
							"x": 1160.7944339999988,
							"y": 209
						},
						"m_scaleX": 1,
						"m_scaleY": 1,
						"m_rotationAngle": 0,
						"m_isArtFlipped": false,
						"m_rotationRate": 0
					},
					{
						"m_eventType": "island",
						"m_imageID": 7,
						"m_parallaxLayer": -4,
						"m_drawLayer": 0,
						"m_position": {
							"x": 10874.706055,
							"y": 455
						},
						"m_scaleX": 1,
						"m_scaleY": 1,
						"m_rotationAngle": 0,
						"m_isArtFlipped": false,
						"m_rotationRate": 18
					},
					{
						"m_eventType": "island",
						"m_imageID": 3,
						"m_parallaxLayer": 0,
						"m_drawLayer": 0,
						"m_position": {
							"x": 651.4499999999999,
							"y": 226
						},
						"m_scaleX": 1,
						"m_scaleY": 1,
						"m_rotationAngle": 0,
						"m_isArtFlipped": false,
						"m_rotationRate": 0
					},
					{
						"m_eventType": "island",
						"m_imageID": 7,
						"m_parallaxLayer": 0,
						"m_drawLayer": 0,
						"m_position": {
							"x": 610.4499999999999,
							"y": 279
						},
						"m_scaleX": 1,
						"m_scaleY": 1,
						"m_rotationAngle": 0,
						"m_isArtFlipped": false,
						"m_rotationRate": 0
					},
					{
						"m_eventType": "island",
						"m_imageID": 24,
						"m_parallaxLayer": 6,
						"m_drawLayer": -1,
						"m_position": {
							"x": 623.6000000000001,
							"y": 361
						},
						"m_scaleX": 0.4,
						"m_scaleY": 0.4,
						"m_rotationAngle": 0,
						"m_isArtFlipped": false,
						"m_rotationRate": 0
					},
					{
						"m_eventType": "island",
						"m_imageID": 34,
						"m_parallaxLayer": 6,
						"m_drawLayer": 0,
						"m_position": {
							"x": 619.0000000000002,
							"y": 303
						},
						"m_scaleX": 1,
						"m_scaleY": 1,
						"m_rotationAngle": 0,
						"m_isArtFlipped": false,
						"m_rotationRate": 0
					},
					{
						"m_eventType": "island",
						"m_imageID": 17,
						"m_parallaxLayer": 6,
						"m_drawLayer": 1,
						"m_position": {
							"x": 630.5,
							"y": 368
						},
						"m_scaleX": 1,
						"m_scaleY": 1,
						"m_rotationAngle": 0,
						"m_isArtFlipped": false,
						"m_rotationRate": 0
					},
					{
						"m_eventType": "island",
						"m_imageID": 8,
						"m_parallaxLayer": 0,
						"m_drawLayer": 0,
						"m_position": {
							"x": 578.28125,
							"y": 390
						},
						"m_scaleX": 1,
						"m_scaleY": 1,
						"m_rotationAngle": 0,
						"m_isArtFlipped": false,
						"m_rotationRate": 0
					},
					{
						"m_eventType": "island",
						"m_imageID": 4,
						"m_parallaxLayer": 0,
						"m_drawLayer": -1,
						"m_position": {
							"x": 584.5312499999999,
							"y": 404
						},
						"m_scaleX": 1,
						"m_scaleY": 1,
						"m_rotationAngle": 0,
						"m_isArtFlipped": false,
						"m_rotationRate": 0
					},
					{
						"m_eventType": "island",
						"m_imageID": 4,
						"m_parallaxLayer": 0,
						"m_drawLayer": 0,
						"m_position": {
							"x": -237.34374999999997,
							"y": 177
						},
						"m_scaleX": 1,
						"m_scaleY": 1,
						"m_rotationAngle": 0,
						"m_isArtFlipped": false,
						"m_rotationRate": 0
					},
					{
						"m_eventType": "island",
						"m_imageID": 4,
						"m_parallaxLayer": 0,
						"m_drawLayer": 0,
						"m_position": {
							"x": -6.986338797813007,
							"y": 211.16393442622962
						},
						"m_scaleX": 1,
						"m_scaleY": 1,
						"m_rotationAngle": 0,
						"m_isArtFlipped": false,
						"m_rotationRate": 0
					},
					{
						"m_eventType": "island",
						"m_imageID": 4,
						"m_parallaxLayer": 0,
						"m_drawLayer": 0,
						"m_position": {
							"x": -267.92383879781295,
							"y": 197.16393442622962
						},
						"m_scaleX": 1,
						"m_scaleY": 1,
						"m_rotationAngle": 0,
						"m_isArtFlipped": false,
						"m_rotationRate": 0
					},
					{
						"m_eventType": "island",
						"m_imageID": 4,
						"m_parallaxLayer": 0,
						"m_drawLayer": 0,
						"m_position": {
							"x": -61.861338797813005,
							"y": 243.16393442622962
						},
						"m_scaleX": 1,
						"m_scaleY": 1,
						"m_rotationAngle": 0,
						"m_isArtFlipped": false,
						"m_rotationRate": 0
					},
					{
						"m_eventType": "island",
						"m_imageID": 4,
						"m_parallaxLayer": 0,
						"m_drawLayer": 0,
						"m_position": {
							"x": -103.86133879781299,
							"y": 275.16393442622956
						},
						"m_scaleX": 1,
						"m_scaleY": 1,
						"m_rotationAngle": 0,
						"m_isArtFlipped": false,
						"m_rotationRate": 0
					},
					{
						"m_eventType": "island",
						"m_imageID": 4,
						"m_parallaxLayer": 0,
						"m_drawLayer": 0,
						"m_position": {
							"x": -156.98633879781303,
							"y": 253.16393442622962
						},
						"m_scaleX": 1,
						"m_scaleY": 1,
						"m_rotationAngle": 0,
						"m_isArtFlipped": false,
						"m_rotationRate": 0
					},
					{
						"m_eventType": "island",
						"m_imageID": 6,
						"m_parallaxLayer": 0,
						"m_drawLayer": 0,
						"m_position": {
							"x": -248.28125,
							"y": 243
						},
						"m_scaleX": 1,
						"m_scaleY": 1,
						"m_rotationAngle": 0,
						"m_isArtFlipped": false,
						"m_rotationRate": 0
					},
					{
						"m_eventType": "island",
						"m_imageID": 15,
						"m_parallaxLayer": 0,
						"m_drawLayer": -1,
						"m_position": {
							"x": -178.86133879781303,
							"y": 216.16393442622962
						},
						"m_scaleX": 1,
						"m_scaleY": 1,
						"m_rotationAngle": 0,
						"m_isArtFlipped": false,
						"m_rotationRate": 0
					},
					{
						"m_eventType": "island",
						"m_imageID": 5,
						"m_parallaxLayer": 0,
						"m_drawLayer": 0,
						"m_position": {
							"x": -20.9375,
							"y": 278
						},
						"m_scaleX": 1,
						"m_scaleY": 1,
						"m_rotationAngle": 0,
						"m_isArtFlipped": false,
						"m_rotationRate": 0
					}
				],
				"m_eventList": [
					{
						"m_position": {
							"x": -547.649994,
							"y": 334.100006
						},
						"m_eventId": 1,
						"m_eventType": "level",
						"m_name": "egypt_level_1",
						"m_parentEvent": "",
						"m_unlockedFrom": "tutorial_level_tutorial4",
						"m_visibleFrom": "",
						"m_autoVisible": true,
						"m_isChallengeType": false,
						"m_dataString": "egypt1",
						"m_levelNodeType": "normal",
						"m_displayText": "1",
						"m_unlockedNarrationID": "",
						"m_completedNarrationID": "",
						"m_worldMapTutorial": "none",
						"m_worldMapTutorialVisibleWhen": "unlocked",
						"m_toggleName": ""
					},
					{
						"m_position": {
							"x": -419,
							"y": 431
						},
						"m_eventId": 2,
						"m_eventType": "level",
						"m_name": "egypt_level_2",
						"m_parentEvent": "egypt_level_1",
						"m_unlockedFrom": "",
						"m_visibleFrom": "",
						"m_autoVisible": true,
						"m_isChallengeType": false,
						"m_dataString": "egypt2",
						"m_levelNodeType": "normal",
						"m_displayText": "2",
						"m_unlockedNarrationID": "",
						"m_completedNarrationID": "",
						"m_worldMapTutorial": "none",
						"m_worldMapTutorialVisibleWhen": "unlocked",
						"m_toggleName": ""
					},
					{
						"m_position": {
							"x": -278,
							"y": 484
						},
						"m_eventId": 3,
						"m_eventType": "level",
						"m_name": "egypt_level_3",
						"m_parentEvent": "egypt_level_2",
						"m_unlockedFrom": "",
						"m_visibleFrom": "",
						"m_autoVisible": true,
						"m_isChallengeType": false,
						"m_dataString": "egypt3",
						"m_levelNodeType": "normal",
						"m_displayText": "3",
						"m_unlockedNarrationID": "",
						"m_completedNarrationID": "",
						"m_worldMapTutorial": "none",
						"m_worldMapTutorialVisibleWhen": "unlocked",
						"m_toggleName": ""
					},
					{
						"m_position": {
							"x": -115,
							"y": 491
						},
						"m_eventId": 4,
						"m_eventType": "level",
						"m_name": "egypt_level_4",
						"m_parentEvent": "egypt_level_3",
						"m_unlockedFrom": "",
						"m_visibleFrom": "",
						"m_autoVisible": true,
						"m_isChallengeType": false,
						"m_dataString": "egypt4",
						"m_levelNodeType": "normal",
						"m_displayText": "4",
						"m_unlockedNarrationID": "",
						"m_completedNarrationID": "",
						"m_worldMapTutorial": "none",
						"m_worldMapTutorialVisibleWhen": "unlocked",
						"m_toggleName": ""
					},
					{
						"m_position": {
							"x": 128,
							"y": 393
						},
						"m_eventId": 5,
						"m_eventType": "level",
						"m_name": "egypt_level_5",
						"m_parentEvent": "egypt_level_4",
						"m_unlockedFrom": "",
						"m_visibleFrom": "",
						"m_autoVisible": true,
						"m_isChallengeType": false,
						"m_dataString": "egypt5",
						"m_levelNodeType": "normal",
						"m_displayText": "5",
						"m_unlockedNarrationID": "",
						"m_completedNarrationID": "",
						"m_worldMapTutorial": "none",
						"m_worldMapTutorialVisibleWhen": "unlocked",
						"m_toggleName": ""
					},
					{
						"m_position": {
							"x": 284,
							"y": 308
						},
						"m_eventId": 6,
						"m_eventType": "level",
						"m_name": "egypt_level_6",
						"m_parentEvent": "egypt_level_5",
						"m_unlockedFrom": "",
						"m_visibleFrom": "",
						"m_autoVisible": true,
						"m_isChallengeType": false,
						"m_dataString": "egypt6",
						"m_levelNodeType": "normal",
						"m_displayText": "6",
						"m_unlockedNarrationID": "",
						"m_completedNarrationID": "",
						"m_worldMapTutorial": "none",
						"m_worldMapTutorialVisibleWhen": "unlocked",
						"m_toggleName": ""
					},
					{
						"m_position": {
							"x": 461,
							"y": 243
						},
						"m_eventId": 7,
						"m_eventType": "level",
						"m_name": "egypt_level_7",
						"m_parentEvent": "egypt_level_6",
						"m_unlockedFrom": "",
						"m_visibleFrom": "",
						"m_autoVisible": true,
						"m_isChallengeType": false,
						"m_dataString": "egypt7",
						"m_levelNodeType": "normal",
						"m_displayText": "7",
						"m_unlockedNarrationID": "",
						"m_completedNarrationID": "",
						"m_worldMapTutorial": "none",
						"m_worldMapTutorialVisibleWhen": "unlocked",
						"m_toggleName": ""
					},
					{
						"m_position": {
							"x": 651,
							"y": 259
						},
						"m_eventId": 8,
						"m_eventType": "level",
						"m_name": "egypt_level_8",
						"m_parentEvent": "egypt_level_7",
						"m_unlockedFrom": "",
						"m_visibleFrom": "",
						"m_autoVisible": true,
						"m_isChallengeType": false,
						"m_dataString": "egypt8",
						"m_levelNodeType": "normal",
						"m_displayText": "8",
						"m_unlockedNarrationID": "",
						"m_completedNarrationID": "",
						"m_worldMapTutorial": "none",
						"m_worldMapTutorialVisibleWhen": "unlocked",
						"m_toggleName": ""
					},
					{
						"m_position": {
							"x": 801,
							"y": 358
						},
						"m_eventId": 9,
						"m_eventType": "level",
						"m_name": "egypt_level_9",
						"m_parentEvent": "egypt_level_8",
						"m_unlockedFrom": "",
						"m_visibleFrom": "",
						"m_autoVisible": true,
						"m_isChallengeType": false,
						"m_dataString": "egypt9",
						"m_levelNodeType": "normal",
						"m_displayText": "9",
						"m_unlockedNarrationID": "",
						"m_completedNarrationID": "",
						"m_worldMapTutorial": "none",
						"m_worldMapTutorialVisibleWhen": "unlocked",
						"m_toggleName": ""
					},
					{
						"m_position": {
							"x": 960,
							"y": 460
						},
						"m_eventId": 10,
						"m_eventType": "level",
						"m_name": "egypt_level_10",
						"m_parentEvent": "egypt_level_9",
						"m_unlockedFrom": "",
						"m_visibleFrom": "",
						"m_autoVisible": true,
						"m_isChallengeType": false,
						"m_dataString": "egypt10",
						"m_levelNodeType": "normal",
						"m_displayText": "10",
						"m_unlockedNarrationID": "",
						"m_completedNarrationID": "",
						"m_worldMapTutorial": "none",
						"m_worldMapTutorialVisibleWhen": "unlocked",
						"m_toggleName": ""
					},
					{
						"m_position": {
							"x": 380,
							"y": 434
						},
						"m_eventId": 5,
						"m_eventType": "level",
						"m_name": "survival_endless_egypt",
						"m_parentEvent": "",
						"m_unlockedFrom": "",
						"m_visibleFrom": "",
						"m_autoVisible": true,
						"m_isChallengeType": true,
						"m_dataString": "survival/survival_egypt",
						"m_levelNodeType": "minigame",
						"m_displayText": "Survival",
						"m_unlockedNarrationID": "",
						"m_completedNarrationID": "",
						"m_worldMapTutorial": "none",
						"m_worldMapTutorialVisibleWhen": "unlocked",
						"m_toggleName": ""
					},
					{
						"m_position": {
							"x": 1182.4,
							"y": 454
						},
						"m_eventId": 11,
						"m_eventType": "level",
						"m_name": "egypt_level_11",
						"m_parentEvent": "egypt_level_10",
						"m_unlockedFrom": "",
						"m_visibleFrom": "",
						"m_autoVisible": true,
						"m_isChallengeType": false,
						"m_dataString": "egypt11",
						"m_levelNodeType": "normal",
						"m_displayText": "11",
						"m_unlockedNarrationID": "",
						"m_completedNarrationID": "",
						"m_worldMapTutorial": "none",
						"m_worldMapTutorialVisibleWhen": "unlocked",
						"m_toggleName": ""
					},
					{
						"m_position": {
							"x": 1336.4,
							"y": 327
						},
						"m_eventId": 12,
						"m_eventType": "level",
						"m_name": "egypt_level_12",
						"m_parentEvent": "egypt_level_11",
						"m_unlockedFrom": "",
						"m_visibleFrom": "",
						"m_autoVisible": true,
						"m_isChallengeType": false,
						"m_dataString": "egypt12",
						"m_levelNodeType": "normal",
						"m_displayText": "12",
						"m_unlockedNarrationID": "",
						"m_completedNarrationID": "",
						"m_worldMapTutorial": "none",
						"m_worldMapTutorialVisibleWhen": "unlocked",
						"m_toggleName": ""
					},
					{
						"m_position": {
							"x": 1507.4,
							"y": 307
						},
						"m_eventId": 13,
						"m_eventType": "level",
						"m_name": "egypt_level_13",
						"m_parentEvent": "egypt_level_12",
						"m_unlockedFrom": "",
						"m_visibleFrom": "",
						"m_autoVisible": true,
						"m_isChallengeType": false,
						"m_dataString": "egypt13",
						"m_levelNodeType": "normal",
						"m_displayText": "13",
						"m_unlockedNarrationID": "",
						"m_completedNarrationID": "",
						"m_worldMapTutorial": "none",
						"m_worldMapTutorialVisibleWhen": "unlocked",
						"m_toggleName": ""
					},
					{
						"m_position": {
							"x": 1691.4,
							"y": 349
						},
						"m_eventId": 14,
						"m_eventType": "level",
						"m_name": "egypt_level_14",
						"m_parentEvent": "egypt_level_13",
						"m_unlockedFrom": "",
						"m_visibleFrom": "",
						"m_autoVisible": true,
						"m_isChallengeType": false,
						"m_dataString": "egypt14",
						"m_levelNodeType": "normal",
						"m_displayText": "14",
						"m_unlockedNarrationID": "",
						"m_completedNarrationID": "",
						"m_worldMapTutorial": "none",
						"m_worldMapTutorialVisibleWhen": "unlocked",
						"m_toggleName": ""
					},
					{
						"m_position": {
							"x": 1821.4,
							"y": 429
						},
						"m_eventId": 15,
						"m_eventType": "level",
						"m_name": "egypt_level_15",
						"m_parentEvent": "egypt_level_14",
						"m_unlockedFrom": "",
						"m_visibleFrom": "",
						"m_autoVisible": true,
						"m_isChallengeType": false,
						"m_dataString": "egypt15",
						"m_levelNodeType": "normal",
						"m_displayText": "15",
						"m_unlockedNarrationID": "",
						"m_completedNarrationID": "",
						"m_worldMapTutorial": "none",
						"m_worldMapTutorialVisibleWhen": "unlocked",
						"m_toggleName": ""
					},
					{
						"m_position": {
							"x": 580,
							"y": 426
						},
						"m_eventId": 10,
						"m_eventType": "level",
						"m_name": "survival_endless_egypt2",
						"m_parentEvent": "",
						"m_unlockedFrom": "",
						"m_visibleFrom": "",
						"m_autoVisible": true,
						"m_isChallengeType": true,
						"m_dataString": "survival/survival_egypt2",
						"m_levelNodeType": "minigame",
						"m_displayText": "Survival II",
						"m_unlockedNarrationID": "",
						"m_completedNarrationID": "",
						"m_worldMapTutorial": "none",
						"m_worldMapTutorialVisibleWhen": "unlocked",
						"m_toggleName": ""
					},
					{
						"m_position": {
							"x": -137.48633879781303,
							"y": 143.1639344262295
						},
						"m_eventId": 50,
						"m_eventType": "level",
						"m_name": "egypt_level_dangerroom",
						"m_parentEvent": "",
						"m_unlockedFrom": "egypt_level_1",
						"m_visibleFrom": "",
						"m_autoVisible": false,
						"m_isChallengeType": false,
						"m_dataString": "egypt_dangerroom",
						"m_levelNodeType": "danger",
						"m_displayText": "10004",
						"m_unlockedNarrationID": "",
						"m_completedNarrationID": "",
						"m_worldMapTutorial": "none",
						"m_worldMapTutorialVisibleWhen": "unlocked",
						"m_toggleName": ""
					}
				]
			}
		}
	]
}